<?xml version="1.0" encoding="utf-8"?>
<?xml-stylesheet type='text/xsl' href='C:\ProgramData\Windows App Certification Kit\results.xsl'?>
<REPORT xml:lang="en-IN" OVERALL_RESULT="WARNING" VERSION="10.0.19041.685" LATEST_VERSION="" UPDATE_DOWNLOAD_URL="" TOOLSET_ARCHITECTURE="x64" SecureBoot="FALSE" APP_TYPE="Centennial" PUBLISHER_DISPLAY_NAME="CN=81CFCF59-AA2B-4985-97BF-4E6A6C36B7D6" APP_NAME="30492SamuelGomes.SchismTracker" APP_VERSION="2022.1.25.0" OSVERSION="10.0.22000.0" OS="Microsoft Windows 11 Home Single Language" PER_USER_APPLICATION="" PARTIAL_RUN="FALSE" LCID="16393" X64_ONLY="TRUE" VALIDATION_TYPE="CommandLine" ReportGenerationTime="27-03-2022 05:41:21 AM" ID="68e729e32416e9df046262b1892ff055">
  <REQUIREMENTS>
    <REQUIREMENT NUMBER="3" TITLE="Digitally signed file test" RATIONALE="An Authenticode digital signature allows users to be sure that the software is genuine. It also allows detection if a file has been tampered with e.g. infected by a virus.">
      <TEST INDEX="2" NAME="Install signed driver and executable files" DESCRIPTION="Install signed driver and executable files." EXECUTIONTIME="00h:00m:01s.22ms" OPTIONAL="TRUE">
        <MESSAGES />
        <RESULT><![CDATA[PASS]]></RESULT>
      </TEST>
    </REQUIREMENT>
    <REQUIREMENT NUMBER="6" TITLE="User account control (UAC) test" RATIONALE="Most applications do not require administrator privileges at run time, and should be just fine running as a standard-user. Windows applications must have a manifest (embedded or external) to define its execution level that tells OS the privileges needed to run the application.">
      <TEST INDEX="11" NAME="User account control run level" DESCRIPTION="Windows® applications must have a manifest (embedded or external) to define its execution level that tells OS the privileges needed to run the application." EXECUTIONTIME="00h:00m:00s.85ms" OPTIONAL="TRUE">
        <MESSAGES />
        <RESULT><![CDATA[PASS]]></RESULT>
      </TEST>
    </REQUIREMENT>
    <REQUIREMENT NUMBER="12" TITLE="Package compliance test" RATIONALE="The package does not satisfy Store compliance rules.">
      <TEST INDEX="77" NAME="Application count" DESCRIPTION="One package should not define more than one app in the manifest." EXECUTIONTIME="00h:00m:00s.99ms" OPTIONAL="TRUE">
        <MESSAGES />
        <RESULT><![CDATA[PASS]]></RESULT>
      </TEST>
      <TEST INDEX="31" NAME="App manifest" DESCRIPTION="App manifest must include valid entries for all required fields." EXECUTIONTIME="00h:00m:01s.46ms" OPTIONAL="FALSE">
        <MESSAGES />
        <RESULT><![CDATA[PASS]]></RESULT>
      </TEST>
      <TEST INDEX="87" NAME="File association verbs" DESCRIPTION="Registry validation that no registered file association verbs are installed." EXECUTIONTIME="00h:00m:00s.88ms" OPTIONAL="TRUE">
        <MESSAGES />
        <RESULT><![CDATA[PASS]]></RESULT>
      </TEST>
      <TEST INDEX="86" NAME="Registry checks" DESCRIPTION="Registry validation that drivers are not installed and NT Services are not installed." EXECUTIONTIME="00h:00m:00s.87ms" OPTIONAL="TRUE">
        <MESSAGES />
        <RESULT><![CDATA[PASS]]></RESULT>
      </TEST>
      <TEST INDEX="91" NAME="Enterprise Features" DESCRIPTION="Check if any enterprise-only features are in the package." EXECUTIONTIME="00h:00m:00s.94ms" OPTIONAL="FALSE">
        <MESSAGES />
        <RESULT><![CDATA[PASS]]></RESULT>
      </TEST>
      <TEST INDEX="90" NAME="Resource Packages" DESCRIPTION="Check if any resource packages contain PE files." EXECUTIONTIME="00h:00m:00s.94ms" OPTIONAL="FALSE">
        <MESSAGES />
        <RESULT><![CDATA[PASS]]></RESULT>
      </TEST>
    </REQUIREMENT>
    <REQUIREMENT NUMBER="14" TITLE="Windows security features test" RATIONALE="Applications must opt-into Windows security features.">
      <TEST INDEX="70" NAME="Banned file analyzer" DESCRIPTION="Analysis of application to detect known insecure files" EXECUTIONTIME="00h:00m:01s.11ms" OPTIONAL="FALSE">
        <MESSAGES />
        <RESULT><![CDATA[PASS]]></RESULT>
      </TEST>
      <TEST INDEX="62" NAME="Private code signing" DESCRIPTION="App should not package private code signing key files." EXECUTIONTIME="00h:00m:01s.17ms" OPTIONAL="FALSE">
        <MESSAGES />
        <RESULT><![CDATA[PASS]]></RESULT>
      </TEST>
    </REQUIREMENT>
    <REQUIREMENT NUMBER="19" TITLE="App manifest resources tests" RATIONALE="The App Package Manifest should have valid resources defined in the resources.pri file, as per the App Packaging Specification and App Manifest Schema.">
      <TEST INDEX="45" NAME="App resources" DESCRIPTION="The package should have valid resources defined in the resources.pri file." EXECUTIONTIME="00h:00m:00s.68ms" OPTIONAL="TRUE">
        <MESSAGES />
        <RESULT><![CDATA[PASS]]></RESULT>
      </TEST>
      <TEST INDEX="61" NAME="Branding" DESCRIPTION="App should not use the default images packed by windows SDK samples or Visual Studio." EXECUTIONTIME="00h:00m:01s.61ms" OPTIONAL="FALSE">
        <MESSAGES />
        <RESULT><![CDATA[PASS]]></RESULT>
      </TEST>
    </REQUIREMENT>
    <REQUIREMENT NUMBER="20" TITLE="Debug configuration test" RATIONALE="The App should not install any debug binaries.">
      <TEST INDEX="46" NAME="Debug configuration" DESCRIPTION="The App should not install any debug binaries." EXECUTIONTIME="00h:00m:01s.47ms" OPTIONAL="TRUE">
        <MESSAGES />
        <RESULT><![CDATA[PASS]]></RESULT>
      </TEST>
    </REQUIREMENT>
    <REQUIREMENT NUMBER="23" TITLE="App Capabilities test" RATIONALE="Packages declaring special-use capabilities will have to provide justifications during the onboarding process.">
      <TEST INDEX="52" NAME="Special use capabilities" DESCRIPTION="Packages declaring special-use capabilities will have to provide justifications during the onboarding process." EXECUTIONTIME="00h:00m:00s.98ms" OPTIONAL="FALSE">
        <MESSAGES />
        <RESULT><![CDATA[PASS]]></RESULT>
      </TEST>
    </REQUIREMENT>
    <REQUIREMENT NUMBER="24" TITLE="Windows Runtime metadata validation" RATIONALE="Metadata needs to be conformant and consistent across all generation sources.">
      <TEST INDEX="56" NAME="ExclusiveTo attribute" DESCRIPTION="A class must not implement an interface that is marked ExclusiveTo another class." EXECUTIONTIME="00h:00m:08s.26ms" OPTIONAL="FALSE">
        <MESSAGES />
        <RESULT><![CDATA[PASS]]></RESULT>
      </TEST>
      <TEST INDEX="57" NAME="Type location" DESCRIPTION="Types must be defined in the metadata file with the longest matching namespace." EXECUTIONTIME="00h:00m:00s.73ms" OPTIONAL="FALSE">
        <MESSAGES />
        <RESULT><![CDATA[PASS]]></RESULT>
      </TEST>
      <TEST INDEX="55" NAME="Type name case-sensitivity" DESCRIPTION="Namespace and type names must not vary only by casing." EXECUTIONTIME="00h:00m:00s.74ms" OPTIONAL="FALSE">
        <MESSAGES />
        <RESULT><![CDATA[PASS]]></RESULT>
      </TEST>
      <TEST INDEX="54" NAME="Type name correctness" DESCRIPTION="Only system types can be in the Windows namespace and no types can be in the global namespace." EXECUTIONTIME="00h:00m:00s.71ms" OPTIONAL="FALSE">
        <MESSAGES />
        <RESULT><![CDATA[PASS]]></RESULT>
      </TEST>
      <TEST INDEX="58" NAME="General metadata correctness" DESCRIPTION="Metadata files must meet various requirements in order to be valid and correct." EXECUTIONTIME="00h:00m:08s.03ms" OPTIONAL="TRUE">
        <MESSAGES />
        <RESULT><![CDATA[PASS]]></RESULT>
      </TEST>
      <TEST INDEX="53" NAME="Properties" DESCRIPTION="Write-only and indexer properties may not be used. Corresponding getter and setter methods must match in type." EXECUTIONTIME="00h:00m:00s.71ms" OPTIONAL="FALSE">
        <MESSAGES />
        <RESULT><![CDATA[PASS]]></RESULT>
      </TEST>
    </REQUIREMENT>
    <REQUIREMENT NUMBER="25" TITLE="Package sanity test" RATIONALE="Validation of the app package contents to ensure correctness.">
      <TEST INDEX="89" NAME="Archive files usage" DESCRIPTION="Packages should not contain PE files inside archive files." EXECUTIONTIME="00h:00m:01s.14ms" OPTIONAL="TRUE">
        <MESSAGES />
        <RESULT><![CDATA[PASS]]></RESULT>
      </TEST>
      <TEST INDEX="88" NAME="Blocked executables" DESCRIPTION="Detects if there are references to process launch APIs and blocked executables" EXECUTIONTIME="00h:00m:01s.42ms" OPTIONAL="TRUE">
        <MESSAGES />
        <RESULT><![CDATA[PASS]]></RESULT>
      </TEST>
      <TEST INDEX="63" NAME="Platform appropriate files" DESCRIPTION="App should not install files that do not match the target processor architecture." EXECUTIONTIME="00h:00m:01s.20ms" OPTIONAL="TRUE">
        <MESSAGES />
        <RESULT><![CDATA[PASS]]></RESULT>
      </TEST>
    </REQUIREMENT>
    <REQUIREMENT NUMBER="26" TITLE="High-DPI support" RATIONALE="The application needs to set DPI-aware to make the UI look consistently good across a wide variety of high-DPI display settings.">
      <TEST INDEX="92" NAME="DPIAwarenessValidation" DESCRIPTION="Applications should set DPI-aware to make its UI look consistently good across a wide variety of high-DPI display settings." EXECUTIONTIME="00h:00m:01s.42ms" OPTIONAL="FALSE">
        <MESSAGES>
          <MESSAGE TEXT="File schismtracker.exe neither has PerMonitorV2 manifested in the manifest nor calls into DPI Awareness APIs for ex: user32!SetProcessDpiAwarenessContext or user32!SetThreadDpiAwarenessContext." />
          <MESSAGE TEXT="The app 30492SamuelGomes.SchismTracker_2022.1.25.0_x64__x6kje0v4c1m1y is not DPI Aware." />
        </MESSAGES>
        <RESULT><![CDATA[WARNING]]></RESULT>
      </TEST>
    </REQUIREMENT>
  </REQUIREMENTS>
  <APPLICATIONS>
    <Installed_Programs>
      <Program Name="30492SamuelGomes.SchismTracker" Type="Application" Source="AppxPackage" Publisher="CN=81CFCF59-AA2B-4985-97BF-4E6A6C36B7D6" Version="2022.1.25.0" Language="16393" InstallDate="" OSVersionAtInstallTime="10.0.0.22000" RootDirPath="C:\Windows\temp\appcert_2B04\30492SamuelGomes.SchismTracker_2022.1.25.0_x64__x6kje0v4c1m1y" Id="0000a6f3baa792fb30531e62793ceff92eb500000940" HiddenArp="false">
        <Indicators>
          <WindowsStoreAppManifestIndicators>
            <PackageManifest PackageFullName="30492SamuelGomes.SchismTracker_2022.1.25.0_x64__x6kje0v4c1m1y">
              <Package>
                <Identity Name="30492SamuelGomes.SchismTracker" Version="2022.1.25.0" Publisher="CN=81CFCF59-AA2B-4985-97BF-4E6A6C36B7D6" ProcessorArchitecture="x64"></Identity>
                <Properties>
                  <DisplayName>Schism Tracker</DisplayName>
                  <PublisherDisplayName>Samuel Gomes</PublisherDisplayName>
                  <Description>Schism Tracker is a free and open-source reimplementation of Impulse Tracker, a program used to create high quality music without the requirements of specialized, expensive equipment, and with a unique 'finger feel' that is difficult to replicate in part. The player is based on a highly modified version of the ModPlug engine, with a number of bugfixes and changes to improve IT playback.</Description>
                  <Logo>Assets\schismtracker50x50.png</Logo>
                </Properties>
                <Resources>
                  <Resource Language="en-us"></Resource>
                </Resources>
                <Dependencies>
                  <TargetDeviceFamily Name="Windows.Desktop" MinVersion="10.0.19041.0" MaxVersionTested="10.0.22000.0"></TargetDeviceFamily>
                </Dependencies>
                <Capabilities>
                  <Capability Name="runFullTrust"></Capability>
                </Capabilities>
                <Applications>
                  <Application Id="SchismTracker" Executable="schismtracker.exe" EntryPoint="Windows.FullTrustApplication">
                    <VisualElements DisplayName="Schism Tracker" Description="Schism Tracker is a free and open-source reimplementation of Impulse Tracker, a program used to create high quality music without the requirements of specialized, expensive equipment, and with a unique 'finger feel' that is difficult to replicate in part. The player is based on a highly modified version of the ModPlug engine, with a number of bugfixes and changes to improve IT playback." Square150x150Logo="Assets\schismtracker150x150.png" Square44x44Logo="Assets\schismtracker44x44.png" BackgroundColor="transparent" ForegroundText="light"></VisualElements>
                    <Extensions>
                      <Extension Category="windows.fileTypeAssociation" EntryPoint="Windows.FullTrustApplication" Executable="schismtracker.exe">
                        <FileTypeAssociation Name=".669">
                          <DisplayName>Tracker Music File</DisplayName>
                          <Logo>Assets\ext.png</Logo>
                          <EditFlags AlwaysUnsafe="false" OpenIsSafe="false"></EditFlags>
                          <SupportedFileTypes>
                            <FileType>.669</FileType>
                            <FileType>.amf</FileType>
                            <FileType>.dmf</FileType>
                            <FileType>.far</FileType>
                            <FileType>.imf</FileType>
                            <FileType>.mdl</FileType>
                            <FileType>.med</FileType>
                            <FileType>.mt2</FileType>
                            <FileType>.mtm</FileType>
                            <FileType>.mus</FileType>
                            <FileType>.okt</FileType>
                            <FileType>.ptm</FileType>
                            <FileType>.sfx</FileType>
                            <FileType>.stm</FileType>
                            <FileType>.ult</FileType>
                          </SupportedFileTypes>
                        </FileTypeAssociation>
                      </Extension>
                      <Extension Category="windows.fileTypeAssociation" EntryPoint="Windows.FullTrustApplication" Executable="schismtracker.exe">
                        <FileTypeAssociation Name=".mid">
                          <DisplayName>MIDI File</DisplayName>
                          <Logo>Assets\midi.png</Logo>
                          <EditFlags AlwaysUnsafe="false" OpenIsSafe="false"></EditFlags>
                          <SupportedFileTypes>
                            <FileType>.mid</FileType>
                            <FileType>.midi</FileType>
                          </SupportedFileTypes>
                        </FileTypeAssociation>
                      </Extension>
                      <Extension Category="windows.fileTypeAssociation" EntryPoint="Windows.FullTrustApplication" Executable="schismtracker.exe">
                        <FileTypeAssociation Name=".it">
                          <DisplayName>Impulse Tracker File</DisplayName>
                          <Logo>Assets\it.png</Logo>
                          <EditFlags AlwaysUnsafe="false" OpenIsSafe="false"></EditFlags>
                          <SupportedFileTypes>
                            <FileType>.it</FileType>
                          </SupportedFileTypes>
                        </FileTypeAssociation>
                      </Extension>
                      <Extension Category="windows.fileTypeAssociation" EntryPoint="Windows.FullTrustApplication" Executable="schismtracker.exe">
                        <FileTypeAssociation Name=".mod">
                          <DisplayName>ProTracker File</DisplayName>
                          <Logo>Assets\mod.png</Logo>
                          <EditFlags AlwaysUnsafe="false" OpenIsSafe="false"></EditFlags>
                          <SupportedFileTypes>
                            <FileType>.mod</FileType>
                          </SupportedFileTypes>
                        </FileTypeAssociation>
                      </Extension>
                      <Extension Category="windows.fileTypeAssociation" EntryPoint="Windows.FullTrustApplication" Executable="schismtracker.exe">
                        <FileTypeAssociation Name=".s3m">
                          <DisplayName>Scream Tracker 3 File</DisplayName>
                          <Logo>Assets\s3m.png</Logo>
                          <EditFlags AlwaysUnsafe="false" OpenIsSafe="false"></EditFlags>
                          <SupportedFileTypes>
                            <FileType>.s3m</FileType>
                          </SupportedFileTypes>
                        </FileTypeAssociation>
                      </Extension>
                      <Extension Category="windows.fileTypeAssociation" EntryPoint="Windows.FullTrustApplication" Executable="schismtracker.exe">
                        <FileTypeAssociation Name=".xm">
                          <DisplayName>FastTracker II File</DisplayName>
                          <Logo>Assets\xm.png</Logo>
                          <EditFlags AlwaysUnsafe="false" OpenIsSafe="false"></EditFlags>
                          <SupportedFileTypes>
                            <FileType>.xm</FileType>
                          </SupportedFileTypes>
                        </FileTypeAssociation>
                      </Extension>
                      <Extension Category="windows.appExecutionAlias" EntryPoint="Windows.FullTrustApplication" Executable="schismtracker.exe">
                        <AppExecutionAlias>
                          <ExecutionAlias Alias="schismtracker.exe"></ExecutionAlias>
                        </AppExecutionAlias>
                      </Extension>
                    </Extensions>
                  </Application>
                </Applications>
              </Package>
            </PackageManifest>
          </WindowsStoreAppManifestIndicators>
        </Indicators>
        <StaticProperties>
          <Files Id="">
            <File Id="00007430ef193469a594074425c028a8a6d93afb9eab" Name="resources.pri" ProductName="" CompanyName="" ProductVersion="" VerLanguage="0" SwitchBackContext="0" FileVersion="" Size="0" SizeOfImage="0" PeHeaderHash="" PeChecksum="0" CrcChecksum="-950046559" BinProductVersion="" BinFileVersion="" FileDescription="" LegalCopyright="" LinkDate="" BinaryType="data_only" LowerCaseLongPath="c:\windows\temp\appcert_2b04\30492samuelgomes.schismtracker_2022.1.25.0_x64__x6kje0v4c1m1y\resources.pri" />
            <File Id="0000aee622d235de77f235e801c688e70e512f013eee" Name="schismtracker.exe" ProductName="schism tracker" CompanyName="storlek" ProductVersion="" VerLanguage="1033" SwitchBackContext="0" FileVersion="" Size="1941504" SizeOfImage="1941504" PeHeaderHash="010192119fe006a49188b25fb5869279cab1ce7b39a6" PeChecksum="1254161" CrcChecksum="-950562964" BinProductVersion="" BinFileVersion="0.2022.1.25" FileDescription="schism tracker" LegalCopyright="copyright © 2003-2012 storlek" LinkDate="01/01/1970 00:00:00" BinaryType="pe64_amd64" LowerCaseLongPath="c:\windows\temp\appcert_2b04\30492samuelgomes.schismtracker_2022.1.25.0_x64__x6kje0v4c1m1y\schismtracker.exe" />
            <File Id="00001c53325dae95f9986e3ac4f7f645ece5d00309fd" Name="SDL.dll" ProductName="simple directmedia layer" CompanyName="" ProductVersion="1, 2, 14, 0" VerLanguage="1033" SwitchBackContext="0" FileVersion="1, 2, 14, 0" Size="471040" SizeOfImage="471040" PeHeaderHash="010151df055225e836da8ed818d8cfa7933bca787bdb" PeChecksum="414504" CrcChecksum="33046124" BinProductVersion="1, 2, 14, 0" BinFileVersion="1.2.14.0" FileDescription="sdl" LegalCopyright="copyright © 2009 sam lantinga" LinkDate="01/01/1970 00:00:00" BinaryType="pe64_amd64" LowerCaseLongPath="c:\windows\temp\appcert_2b04\30492samuelgomes.schismtracker_2022.1.25.0_x64__x6kje0v4c1m1y\sdl.dll" />
          </Files>
        </StaticProperties>
      </Program>
    </Installed_Programs>
  </APPLICATIONS>
  <DEPENDENCY_INFORMATION>
    <AitStaticAnalysis ProgramId="0000da39a3ee5e6b4b0d3255bfef95601890afd80709" AnalysisVersion="1.70" DictionaryVersion="3.6" Type="Max" Id="C:\Windows\temp\appcert_2B04\30492SamuelGomes.SchismTracker_2022.1.25.0_x64__x6kje0v4c1m1y">
      <AitFile ErrorCode="0" Name="SDL.dll" Id="00001c53325dae95f9986e3ac4f7f645ece5d00309fd">
        <AitCategory Id="Com">
          <AitFeature Name="{00000000-0000-0000-0000-000000000001}" />
          <AitFeature Name="{00000000-0000-0000-0000-000000000010}" />
          <AitFeature Name="{00000000-0000-0000-c000-000000000046}" />
          <AitFeature Name="{00000001-0000-0000-c000-000000000046}" />
          <AitFeature Name="{00000002-0000-0000-c000-000000000046}" />
          <AitFeature Name="{00000003-0000-0000-c000-000000000046}" />
          <AitFeature Name="{0000000a-0000-0000-c000-000000000046}" />
          <AitFeature Name="{0000000b-0000-0000-c000-000000000046}" />
          <AitFeature Name="{0000000c-0000-0000-c000-000000000046}" />
          <AitFeature Name="{0000000d-0000-0000-c000-000000000046}" />
          <AitFeature Name="{0000000e-0000-0000-c000-000000000046}" />
          <AitFeature Name="{0000000f-0000-0000-c000-000000000046}" />
          <AitFeature Name="{00000010-0000-0000-c000-000000000046}" />
          <AitFeature Name="{00000012-0000-0000-c000-000000000046}" />
          <AitFeature Name="{00000016-0000-0000-c000-000000000046}" />
          <AitFeature Name="{00000018-0000-0000-c000-000000000046}" />
          <AitFeature Name="{00000019-0000-0000-c000-000000000046}" />
          <AitFeature Name="{0000001d-0000-0000-c000-000000000046}" />
          <AitFeature Name="{00000020-0000-0000-c000-000000000046}" />
          <AitFeature Name="{00000021-0000-0000-c000-000000000046}" />
          <AitFeature Name="{00000022-0000-0000-c000-000000000046}" />
          <AitFeature Name="{00000025-0000-0000-c000-000000000046}" />
          <AitFeature Name="{00000026-0000-0000-c000-000000000046}" />
          <AitFeature Name="{00000029-0000-0000-c000-000000000046}" />
          <AitFeature Name="{0000002a-0000-0000-c000-000000000046}" />
          <AitFeature Name="{0000002b-0000-0000-c000-000000000046}" />
          <AitFeature Name="{0000002d-0000-0000-c000-000000000046}" />
          <AitFeature Name="{0000002e-0000-0000-c000-000000000046}" />
          <AitFeature Name="{0000002f-0000-0000-c000-000000000046}" />
          <AitFeature Name="{00000030-0000-0000-c000-000000000046}" />
          <AitFeature Name="{00000031-0000-0000-c000-000000000046}" />
          <AitFeature Name="{00000032-0000-0000-c000-000000000046}" />
          <AitFeature Name="{00000033-0000-0000-c000-000000000046}" />
          <AitFeature Name="{00000034-0000-0000-c000-000000000046}" />
          <AitFeature Name="{00000040-0000-0000-c000-000000000046}" />
          <AitFeature Name="{00000100-0000-0000-c000-000000000046}" />
          <AitFeature Name="{00000101-0000-0000-c000-000000000046}" />
          <AitFeature Name="{00000102-0000-0000-c000-000000000046}" />
          <AitFeature Name="{00000103-0000-0000-c000-000000000046}" />
          <AitFeature Name="{00000104-0000-0000-c000-000000000046}" />
          <AitFeature Name="{00000105-0000-0000-c000-000000000046}" />
          <AitFeature Name="{00000109-0000-0000-c000-000000000046}" />
          <AitFeature Name="{0000010a-0000-0000-c000-000000000046}" />
          <AitFeature Name="{0000010b-0000-0000-c000-000000000046}" />
          <AitFeature Name="{0000010c-0000-0000-c000-000000000046}" />
          <AitFeature Name="{0000010d-0000-0000-c000-000000000046}" />
          <AitFeature Name="{0000010e-0000-0000-c000-000000000046}" />
          <AitFeature Name="{0000010f-0000-0000-c000-000000000046}" />
          <AitFeature Name="{00000110-0000-0000-c000-000000000046}" />
          <AitFeature Name="{00000111-0000-0000-c000-000000000046}" />
          <AitFeature Name="{00000112-0000-0000-c000-000000000046}" />
          <AitFeature Name="{00000113-0000-0000-c000-000000000046}" />
          <AitFeature Name="{00000114-0000-0000-c000-000000000046}" />
          <AitFeature Name="{00000115-0000-0000-c000-000000000046}" />
          <AitFeature Name="{00000116-0000-0000-c000-000000000046}" />
          <AitFeature Name="{00000117-0000-0000-c000-000000000046}" />
          <AitFeature Name="{00000118-0000-0000-c000-000000000046}" />
          <AitFeature Name="{00000119-0000-0000-c000-000000000046}" />
          <AitFeature Name="{0000011a-0000-0000-c000-000000000046}" />
          <AitFeature Name="{0000011b-0000-0000-c000-000000000046}" />
          <AitFeature Name="{0000011c-0000-0000-c000-000000000046}" />
          <AitFeature Name="{0000011d-0000-0000-c000-000000000046}" />
          <AitFeature Name="{0000011e-0000-0000-c000-000000000046}" />
          <AitFeature Name="{00000121-0000-0000-c000-000000000046}" />
          <AitFeature Name="{00000122-0000-0000-c000-000000000046}" />
          <AitFeature Name="{00000125-0000-0000-c000-000000000046}" />
          <AitFeature Name="{00000126-0000-0000-c000-000000000046}" />
          <AitFeature Name="{00000127-0000-0000-c000-000000000046}" />
          <AitFeature Name="{00000128-0000-0000-c000-000000000046}" />
          <AitFeature Name="{00000129-0000-0000-c000-000000000046}" />
          <AitFeature Name="{0000012a-0000-0000-c000-000000000046}" />
          <AitFeature Name="{0000012b-0000-0000-c000-000000000046}" />
          <AitFeature Name="{00000138-0000-0000-c000-000000000046}" />
          <AitFeature Name="{00000139-0000-0000-c000-000000000046}" />
          <AitFeature Name="{0000013a-0000-0000-c000-000000000046}" />
          <AitFeature Name="{0000013b-0000-0000-c000-000000000046}" />
          <AitFeature Name="{0000013d-0000-0000-c000-000000000046}" />
          <AitFeature Name="{0000013e-0000-0000-c000-000000000046}" />
          <AitFeature Name="{00000140-0000-0000-c000-000000000046}" />
          <AitFeature Name="{00000144-0000-0000-c000-000000000046}" />
          <AitFeature Name="{00000145-0000-0000-c000-000000000046}" />
          <AitFeature Name="{00000146-0000-0000-c000-000000000046}" />
          <AitFeature Name="{00000147-0000-0000-c000-000000000046}" />
          <AitFeature Name="{00000148-0000-0000-c000-000000000046}" />
          <AitFeature Name="{00000149-0000-0000-c000-000000000046}" />
          <AitFeature Name="{00000150-0000-0000-c000-000000000046}" />
          <AitFeature Name="{00000151-0000-0000-c000-000000000046}" />
          <AitFeature Name="{0000015b-0000-0000-c000-000000000046}" />
          <AitFeature Name="{000001ce-0000-0000-c000-000000000046}" />
          <AitFeature Name="{000001cf-0000-0000-c000-000000000046}" />
          <AitFeature Name="{000001d4-0000-0000-c000-000000000046}" />
          <AitFeature Name="{000001d5-0000-0000-c000-000000000046}" />
          <AitFeature Name="{00020400-0000-0000-c000-000000000046}" />
          <AitFeature Name="{00020401-0000-0000-c000-000000000046}" />
          <AitFeature Name="{00020402-0000-0000-c000-000000000046}" />
          <AitFeature Name="{00020403-0000-0000-c000-000000000046}" />
          <AitFeature Name="{00020404-0000-0000-c000-000000000046}" />
          <AitFeature Name="{00020405-0000-0000-c000-000000000046}" />
          <AitFeature Name="{00020406-0000-0000-c000-000000000046}" />
          <AitFeature Name="{0002040e-0000-0000-c000-000000000046}" />
          <AitFeature Name="{0002040f-0000-0000-c000-000000000046}" />
          <AitFeature Name="{00020410-0000-0000-c000-000000000046}" />
          <AitFeature Name="{00020411-0000-0000-c000-000000000046}" />
          <AitFeature Name="{00020412-0000-0000-c000-000000000046}" />
          <AitFeature Name="{000e0000-0000-0000-c000-000000000046}" />
          <AitFeature Name="{000e0020-0000-0000-c000-000000000046}" />
          <AitFeature Name="{00990df4-0dbb-4872-833e-6d303e80aeb6}" />
          <AitFeature Name="{00e48f7b-d2c8-49e8-a86c-022dee53431f}" />
          <AitFeature Name="{0194c220-a303-11d0-9c4f-00a0c905425e}" />
          <AitFeature Name="{01e44665-24ac-101b-84ed-08002b2ec713}" />
          <AitFeature Name="{02177241-69fc-400c-8ff1-93a44df6861d}" />
          <AitFeature Name="{02538130-898f-11d0-9ad0-00a0c9a06e35}" />
          <AitFeature Name="{035f3ab4-482e-4e50-b41f-8a7f8bd8960b}" />
          <AitFeature Name="{037e866e-f56d-4357-a8af-9dabbe6e250e}" />
          <AitFeature Name="{03823efb-8d8f-4e1c-9aa2-f64bb2cbfdf1}" />
          <AitFeature Name="{05eec05d-8f7d-4362-b999-d1baf357c704}" />
          <AitFeature Name="{06675a80-3b9b-11d2-b92f-00609797ea5b}" />
          <AitFeature Name="{0803425a-57f5-4dd6-9465-a87570834a08}" />
          <AitFeature Name="{08f2d8c9-37c2-11d2-b9f9-0000f875ac12}" />
          <AitFeature Name="{0ab1c530-4745-11d1-a7a1-0000f803abfc}" />
          <AitFeature Name="{0ab1c531-4745-11d1-a7a1-0000f803abfc}" />
          <AitFeature Name="{0b2b8630-ad35-11d0-8ea6-00609797ea5b}" />
          <AitFeature Name="{0c733a30-2a1c-11ce-ade5-00aa0044773d}" />
          <AitFeature Name="{0cfbaf3a-9ff6-429a-99b3-a2796af8b89b}" />
          <AitFeature Name="{0d22ee73-4a46-4a0d-89b2-045b4d666425}" />
          <AitFeature Name="{0e689c9a-053d-44a0-9d92-db0e3d750f86}" />
          <AitFeature Name="{0e6d4d90-6738-11cf-9608-00aa00680db4}" />
          <AitFeature Name="{0e6d4d92-6738-11cf-9608-00aa00680db4}" />
          <AitFeature Name="{0f1d6860-88d9-11cf-9c4e-00a0c905425e}" />
          <AitFeature Name="{1008c4a0-7613-11cf-9af1-0020af6e72f4}" />
          <AitFeature Name="{10ec4d5b-975a-4689-b9e4-d0aac30fe333}" />
          <AitFeature Name="{11ab3ec0-25ec-11d1-a4d8-00c04fc28aca}" />
          <AitFeature Name="{11c81bc2-121e-4ed5-b9c4-b430bd54f2c0}" />
          <AitFeature Name="{11ec5a5f-51dc-4945-ab34-6e8c21300ea5}" />
          <AitFeature Name="{120ced89-3bf4-4173-a132-3cb406cf3231}" />
          <AitFeature Name="{133efe40-32dc-11d0-9cfb-00a0c90a43cb}" />
          <AitFeature Name="{133efe41-32dc-11d0-9cfb-00a0c90a43cb}" />
          <AitFeature Name="{15e65ec0-3b9c-11d2-b92f-00609797ea5b}" />
          <AitFeature Name="{1841e5c8-16b0-489b-bcc8-44cfb0d5deae}" />
          <AitFeature Name="{1b36bb7b-09b7-410a-b445-7d1430d7b33f}" />
          <AitFeature Name="{1b940b17-2642-4d1f-ab1f-b99bad0c395f}" />
          <AitFeature Name="{1bb4af80-a303-11d0-9c4f-00a0c905425e}" />
          <AitFeature Name="{1bf63c95-2650-405d-99c1-3636bd1da0a1}" />
          <AitFeature Name="{1c2056cc-5ef4-101b-8bc8-00aa003e3b29}" />
          <AitFeature Name="{1c733a30-2a1c-11ce-ade5-00aa0044773d}" />
          <AitFeature Name="{1cf2b120-547d-101b-8e65-08002b2bd119}" />
          <AitFeature Name="{1d7b0652-185f-41c6-85ce-0c5be3d4ae6c}" />
          <AitFeature Name="{1dd9e8da-1c77-4d40-b0cf-98fefdff9512}" />
          <AitFeature Name="{1de12ab1-c9f5-11cf-bfc7-444553540000}" />
          <AitFeature Name="{1ef337e3-58e7-4f83-a692-db221f5ed47e}" />
          <AitFeature Name="{1fcd2294-df6d-4eae-86b3-0e9160cfb07b}" />
          <AitFeature Name="{21af9f0e-4d94-4ea9-9785-2cb76b8c0b34}" />
          <AitFeature Name="{22f03340-547d-101b-8e65-08002b2bd119}" />
          <AitFeature Name="{22f55881-280b-11d0-a8a9-00a0c90c2004}" />
          <AitFeature Name="{22f55882-280b-11d0-a8a9-00a0c90c2004}" />
          <AitFeature Name="{2411e7e1-12ac-4ccf-bd14-9798e8534dc0}" />
          <AitFeature Name="{24f416e6-1f67-4aa7-b88e-d33f6f3128a1}" />
          <AitFeature Name="{2518526c-e789-4111-a7b9-47ef328d13e6}" />
          <AitFeature Name="{25b15600-0115-11d0-bf0d-00aa00b8dfd2}" />
          <AitFeature Name="{25e609e0-b259-11cf-bfc7-444553540000}" />
          <AitFeature Name="{25e609e1-b259-11cf-bfc7-444553540000}" />
          <AitFeature Name="{25e609e4-b259-11cf-bfc7-444553540000}" />
          <AitFeature Name="{25e609e5-b259-11cf-bfc7-444553540000}" />
          <AitFeature Name="{26c66a70-b367-11cf-a024-00aa006157ac}" />
          <AitFeature Name="{279afa83-4981-11ce-a521-0020af0be560}" />
          <AitFeature Name="{279afa84-4981-11ce-a521-0020af0be560}" />
          <AitFeature Name="{279afa85-4981-11ce-a521-0020af0be560}" />
          <AitFeature Name="{279afa86-4981-11ce-a521-0020af0be560}" />
          <AitFeature Name="{286f484d-375e-4458-a272-b138e2f80a6a}" />
          <AitFeature Name="{28acf509-7f5c-48f6-8611-f316010a6380}" />
          <AitFeature Name="{28ca0cc3-c2c9-40bb-b57f-67b737122b17}" />
          <AitFeature Name="{28f54685-06fd-11d2-b27a-00a0c9223196}" />
          <AitFeature Name="{29038f61-3839-4626-91fd-086879011a05}" />
          <AitFeature Name="{2accfe60-c130-11d2-b082-00a0c91efb8b}" />
          <AitFeature Name="{2ad1edaf-d83d-48b5-9adf-03dbe19f53bd}" />
          <AitFeature Name="{2b4b1cc8-a4ad-41f8-8322-ca86fc3ec675}" />
          <AitFeature Name="{2b74f7c0-9154-11cf-a9cd-00aa006886e3}" />
          <AitFeature Name="{2cdcd9e0-25a0-11cf-a31a-00aa00b93356}" />
          <AitFeature Name="{2d3629f7-813d-4939-8508-f05c6b75fd97}" />
          <AitFeature Name="{2db72490-652c-11d1-a7a8-0000f803abfc}" />
          <AitFeature Name="{2db72491-652c-11d1-a7a8-0000f803abfc}" />
          <AitFeature Name="{2fe8f810-b2a5-11d0-a787-0000f803abfc}" />
          <AitFeature Name="{3015a308-dcbd-47aa-a747-192486d14d4a}" />
          <AitFeature Name="{30f3d47a-6447-11d1-8e3c-00c04fb9386d}" />
          <AitFeature Name="{310d36a0-d2e7-4c0a-aa04-6a9d23b8886a}" />
          <AitFeature Name="{3127ca40-446e-11ce-8135-00aa004bb851}" />
          <AitFeature Name="{31627037-53ab-4200-9061-05faa9ab45f9}" />
          <AitFeature Name="{31efac30-515c-11d0-a9aa-00aa0061be93}" />
          <AitFeature Name="{36e95ee0-8577-11cf-960c-0080c7534e82}" />
          <AitFeature Name="{376bd3aa-3845-101b-84ed-08002b2ec713}" />
          <AitFeature Name="{37d84f60-42cb-11ce-8135-00aa004bb851}" />
          <AitFeature Name="{38325b96-effb-4022-ba02-2e795b70275c}" />
          <AitFeature Name="{3901cc3f-84b5-4fa4-ba35-aa8172b8a09b}" />
          <AitFeature Name="{3af24290-0c96-11ce-a0cf-00aa00600ab8}" />
          <AitFeature Name="{3af24292-0c96-11ce-a0cf-00aa00600ab8}" />
          <AitFeature Name="{3af280b6-cb3f-11d0-891e-00c04fb6bfc4}" />
          <AitFeature Name="{3b2b6775-70b6-45af-8dea-a209c69559f3}" />
          <AitFeature Name="{3b301d64-d678-4289-8897-22f8928b72f3}" />
          <AitFeature Name="{3bba0080-2421-11cf-a31a-00aa00b93356}" />
          <AitFeature Name="{3c305196-50db-11d3-9cfe-00c04fd930c5}" />
          <AitFeature Name="{3c9c5b51-995d-48d1-9b8d-fa5caeded65c}" />
          <AitFeature Name="{3d3e0379-f9de-4d58-bb6c-18d62992f1a6}" />
          <AitFeature Name="{3d82ab40-62da-11cf-ab39-0020af71e433}" />
          <AitFeature Name="{3d82ab41-62da-11cf-ab39-0020af71e433}" />
          <AitFeature Name="{3d82ab42-62da-11cf-ab39-0020af71e433}" />
          <AitFeature Name="{3d82ab43-62da-11cf-ab39-0020af71e433}" />
          <AitFeature Name="{3d82ab44-62da-11cf-ab39-0020af71e433}" />
          <AitFeature Name="{3d82ab45-62da-11cf-ab39-0020af71e433}" />
          <AitFeature Name="{3d82ab46-62da-11cf-ab39-0020af71e433}" />
          <AitFeature Name="{3e02c918-cc79-4985-b622-2d92ad701623}" />
          <AitFeature Name="{3ee5b968-2aca-4c34-8bb5-7e0c3d19b750}" />
          <AitFeature Name="{4108fa85-3586-11d3-8bd7-00600893b1b6}" />
          <AitFeature Name="{4221b2e1-8955-46c0-bd5b-de9897565de7}" />
          <AitFeature Name="{4417c142-33ad-11cf-816f-0000c020156e}" />
          <AitFeature Name="{4417c144-33ad-11cf-816f-0000c020156e}" />
          <AitFeature Name="{4417c145-33ad-11cf-816f-0000c020156e}" />
          <AitFeature Name="{4417c146-33ad-11cf-816f-0000c020156e}" />
          <AitFeature Name="{44eaa760-cb68-11cf-9c4e-00a0c905425e}" />
          <AitFeature Name="{4516ec43-8f20-11d0-9b6d-0000c0781bc3}" />
          <AitFeature Name="{46858c3a-0dc6-45e3-b760-d4eef16cb325}" />
          <AitFeature Name="{469e07f7-045a-48d5-aa12-68a478cdf75d}" />
          <AitFeature Name="{47d4d946-62e8-11cf-93bc-444553540000}" />
          <AitFeature Name="{480ff4b0-28b2-11d1-bef7-00c04fbf8fef}" />
          <AitFeature Name="{48570b85-d1ee-4fcd-a250-eb350722b037}" />
          <AitFeature Name="{4968b601-9d00-4cde-8346-8e7f675819b6}" />
          <AitFeature Name="{4ae63092-6327-4c1b-80ae-bfe12ea32b86}" />
          <AitFeature Name="{4b166a6a-0d66-43f3-80e3-ee6280dee1a4}" />
          <AitFeature Name="{4b35d0cd-1e15-4258-9c98-1b1333f6dd3b}" />
          <AitFeature Name="{4b8aaafa-140f-42ba-9131-597eafaa2ead}" />
          <AitFeature Name="{4b9f0ee0-0d7e-11d0-9b06-00a0c903a3b8}" />
          <AitFeature Name="{4bbd1154-62f6-4e2c-a15c-d3b6c417f7a0}" />
          <AitFeature Name="{4be0537b-5c19-11d3-8bdc-00600893b1b6}" />
          <AitFeature Name="{4d36e96b-e325-11ce-bfc1-08002be10318}" />
          <AitFeature Name="{4d36e96c-e325-11ce-bfc1-08002be10318}" />
          <AitFeature Name="{4d36e96f-e325-11ce-bfc1-08002be10318}" />
          <AitFeature Name="{4d36e978-e325-11ce-bfc1-08002be10318}" />
          <AitFeature Name="{4e9e1ddc-cd9d-4772-a837-00180b9b88fd}" />
          <AitFeature Name="{4ef6100a-af88-11d0-9846-00c04fc29993}" />
          <AitFeature Name="{4f5b196e-c2bd-495e-bd01-1fded38e4969}" />
          <AitFeature Name="{4f9f9fcb-e0f4-48eb-b7ab-fa2ea9365cb4}" />
          <AitFeature Name="{50666c24-b82f-4eed-a172-5b6e7e8522e0}" />
          <AitFeature Name="{50936643-13e9-11d1-89aa-00a0c9054129}" />
          <AitFeature Name="{509aaeda-5639-11d1-b6a1-0000f8757bf9}" />
          <AitFeature Name="{5102dacd-241b-11d3-aea7-006097b01411}" />
          <AitFeature Name="{5102dace-241b-11d3-aea7-006097b01411}" />
          <AitFeature Name="{5102dacf-241b-11d3-aea7-006097b01411}" />
          <AitFeature Name="{51191f1e-4f2b-11d1-8cc3-00a0c90629a8}" />
          <AitFeature Name="{51b0ca8b-ec0b-4519-870d-8ee1cb5017c7}" />
          <AitFeature Name="{51f23923-f3e5-4bd1-91cb-606177d8db4c}" />
          <AitFeature Name="{53934290-628d-11d2-ae0f-006097b01411}" />
          <AitFeature Name="{53c84785-8425-4dc5-971b-e58d9c19f9b6}" />
          <AitFeature Name="{53f56307-b6bf-11d0-94f2-00a0c91efb8b}" />
          <AitFeature Name="{53f56308-b6bf-11d0-94f2-00a0c91efb8b}" />
          <AitFeature Name="{53f5630b-b6bf-11d0-94f2-00a0c91efb8b}" />
          <AitFeature Name="{53f5630d-b6bf-11d0-94f2-00a0c91efb8b}" />
          <AitFeature Name="{53f56311-b6bf-11d0-94f2-00a0c91efb8b}" />
          <AitFeature Name="{54533251-82be-4824-96c1-47b60b740d00}" />
          <AitFeature Name="{5454e9a0-db65-11ce-921c-00aa006c4972}" />
          <AitFeature Name="{54d41080-dc15-4833-a41b-748f73a38179}" />
          <AitFeature Name="{54d41081-dc15-4833-a41b-748f73a38179}" />
          <AitFeature Name="{54ec77fa-1377-44e6-8c32-88fd5f44c84c}" />
          <AitFeature Name="{55272a00-42cb-11ce-8135-00aa004bb851}" />
          <AitFeature Name="{55980ba0-35aa-11cf-b671-00aa004cd6d8}" />
          <AitFeature Name="{55a8fd00-4288-11d3-9bd1-8a0d61c88835}" />
          <AitFeature Name="{56648f4d-cc8b-4444-a5ad-b5a3d76e91b3}" />
          <AitFeature Name="{56a86897-0ad4-11ce-b03a-0020af0ba770}" />
          <AitFeature Name="{57805885-6eec-11cf-9441-a82303c10e27}" />
          <AitFeature Name="{57b6c80a-34c2-4602-bc26-66a02fc57153}" />
          <AitFeature Name="{57d7c6bc-2356-11d3-8e9d-00c04f6844ae}" />
          <AitFeature Name="{57d7c6bd-2356-11d3-8e9d-00c04f6844ae}" />
          <AitFeature Name="{580ca87e-1d3c-4d54-991d-b7d3e3c298ce}" />
          <AitFeature Name="{5852a2c3-6530-11d1-b6a3-0000f8757bf9}" />
          <AitFeature Name="{58a08519-24c8-4935-b482-3fd823333a4f}" />
          <AitFeature Name="{58c2b4d0-46e7-11d1-89ac-00a0c9054129}" />
          <AitFeature Name="{593817a0-7db3-11cf-a2de-00aa00b93356}" />
          <AitFeature Name="{5944e662-aa8a-11cf-bfc7-444553540000}" />
          <AitFeature Name="{5944e663-aa8a-11cf-bfc7-444553540000}" />
          <AitFeature Name="{5944e680-c92e-11cf-bfc7-444553540000}" />
          <AitFeature Name="{5944e681-c92e-11cf-bfc7-444553540000}" />
          <AitFeature Name="{5944e682-c92e-11cf-bfc7-444553540000}" />
          <AitFeature Name="{5944e683-c92e-11cf-bfc7-444553540000}" />
          <AitFeature Name="{594f31d0-7f19-11d0-b194-00a0c90dc8bf}" />
          <AitFeature Name="{5cfbeb89-1a06-46e0-b282-e3f9bfa36a54}" />
          <AitFeature Name="{61f21c45-3c0e-4a74-9cea-67100d9ad5e4}" />
          <AitFeature Name="{62b98c44-1f82-4c67-bcd0-72cf8f217e81}" />
          <AitFeature Name="{6316be88-54cd-4040-ab44-20461bc81f68}" />
          <AitFeature Name="{636b9f10-0c7d-11d1-95b2-0020afdc7421}" />
          <AitFeature Name="{64108800-957d-11d0-89ab-00a0c9054129}" />
          <AitFeature Name="{6530d5c7-07e9-4271-a418-e7ce4bd1e480}" />
          <AitFeature Name="{6536115a-7b2d-11d2-ba18-0000f875ac12}" />
          <AitFeature Name="{6543dbb6-1b48-42f5-ab82-e97ec74326f6}" />
          <AitFeature Name="{667955ad-6b3b-43ca-b949-bc69b5baff7f}" />
          <AitFeature Name="{66c66a94-dddd-4b62-a66a-f0da33c2b4d0}" />
          <AitFeature Name="{6825a449-7524-4d82-920f-50e36ab3ab1e}" />
          <AitFeature Name="{69c11c3e-b46b-11d1-ad7a-00c04fc29b4e}" />
          <AitFeature Name="{69d14c80-c18e-11d0-a9ce-006097942311}" />
          <AitFeature Name="{6aae1ec1-662a-11d0-889d-00aa00bbb76a}" />
          <AitFeature Name="{6c142760-a733-11ce-a521-0020af0be560}" />
          <AitFeature Name="{6c14db80-a733-11ce-a521-0020af0be560}" />
          <AitFeature Name="{6c14db81-a733-11ce-a521-0020af0be560}" />
          <AitFeature Name="{6c14db84-a733-11ce-a521-0020af0be560}" />
          <AitFeature Name="{6c14db85-a733-11ce-a521-0020af0be560}" />
          <AitFeature Name="{6d3bdbdc-5b02-4415-b852-ce5e8bccb289}" />
          <AitFeature Name="{6d4a3650-628d-11d2-ae0f-006097b01411}" />
          <AitFeature Name="{6d5140c1-7436-11ce-8034-00aa006009fa}" />
          <AitFeature Name="{6e6ffa6a-9bae-4613-a51e-91652d508c21}" />
          <AitFeature Name="{6e8c49fb-a371-4770-b440-29086022b741}" />
          <AitFeature Name="{6f15aaf2-d208-4e89-9ab4-489535d34f9c}" />
          <AitFeature Name="{6fc2cae1-bc78-11d2-afa6-00aa0024d8b6}" />
          <AitFeature Name="{70bdde00-c18e-11d0-a9ce-006097942311}" />
          <AitFeature Name="{711c7600-6b48-11d1-b403-00aa00b92af1}" />
          <AitFeature Name="{71417501-8df9-4e0a-a78a-255f9756baff}" />
          <AitFeature Name="{72380d55-8d2b-43a3-8513-2b6ef31434e9}" />
          <AitFeature Name="{7385e5df-8fe8-41d5-86b6-d7b48547b6cf}" />
          <AitFeature Name="{742b0e01-14e6-101b-914e-00aa00300cab}" />
          <AitFeature Name="{743b5d60-628d-11d2-ae0f-006097b01411}" />
          <AitFeature Name="{743f1dc6-5aba-429f-8bdf-c54d03253dc2}" />
          <AitFeature Name="{745a17a0-74d3-11d0-b6fe-00a0c90f57da}" />
          <AitFeature Name="{75b68faa-347d-4159-8f45-a0640f01cd9a}" />
          <AitFeature Name="{770aae78-f26f-4dba-a829-253c83d1b387}" />
          <AitFeature Name="{77db970f-6276-48ba-ba28-070143b4392c}" />
          <AitFeature Name="{7857aeac-d31f-49bf-884e-dd46df36780a}" />
          <AitFeature Name="{78ec89a0-e0af-11cf-9c4e-00a0c905425e}" />
          <AitFeature Name="{794950f2-adfc-458a-905e-10a10b0b503b}" />
          <AitFeature Name="{79ba9e00-b6ee-11d1-86be-00c04fbf8fef}" />
          <AitFeature Name="{79cf2233-7536-4948-9d36-1e4692dc5760}" />
          <AitFeature Name="{79eac9c0-baf9-11ce-8c82-00aa004ba90b}" />
          <AitFeature Name="{79eac9c1-baf9-11ce-8c82-00aa004ba90b}" />
          <AitFeature Name="{79eac9c9-baf9-11ce-8c82-00aa004ba90b}" />
          <AitFeature Name="{79eac9cd-baf9-11ce-8c82-00aa004ba90b}" />
          <AitFeature Name="{79eac9d0-baf9-11ce-8c82-00aa004ba90b}" />
          <AitFeature Name="{79eac9d1-baf9-11ce-8c82-00aa004ba90b}" />
          <AitFeature Name="{79eac9d2-baf9-11ce-8c82-00aa004ba90b}" />
          <AitFeature Name="{79eac9d5-bafa-11ce-8c82-00aa004ba90b}" />
          <AitFeature Name="{79eac9d6-bafa-11ce-8c82-00aa004ba90b}" />
          <AitFeature Name="{79eac9d7-bafa-11ce-8c82-00aa004ba90b}" />
          <AitFeature Name="{79eac9d8-bafa-11ce-8c82-00aa004ba90b}" />
          <AitFeature Name="{79eac9e0-baf9-11ce-8c82-00aa004ba90b}" />
          <AitFeature Name="{79eac9e1-baf9-11ce-8c82-00aa004ba90b}" />
          <AitFeature Name="{79eac9e3-baf9-11ce-8c82-00aa004ba90b}" />
          <AitFeature Name="{79eac9e4-baf9-11ce-8c82-00aa004ba90b}" />
          <AitFeature Name="{79eac9e5-baf9-11ce-8c82-00aa004ba90b}" />
          <AitFeature Name="{79eac9e7-baf9-11ce-8c82-00aa004ba90b}" />
          <AitFeature Name="{79eac9e8-baf9-11ce-8c82-00aa004ba90b}" />
          <AitFeature Name="{79eac9eb-baf9-11ce-8c82-00aa004ba90b}" />
          <AitFeature Name="{79eac9ec-baf9-11ce-8c82-00aa004ba90b}" />
          <AitFeature Name="{79eac9ed-baf9-11ce-8c82-00aa004ba90b}" />
          <AitFeature Name="{79eac9ee-baf9-11ce-8c82-00aa004ba90b}" />
          <AitFeature Name="{79eac9ef-baf9-11ce-8c82-00aa004ba90b}" />
          <AitFeature Name="{79eac9f0-baf9-11ce-8c82-00aa004ba90b}" />
          <AitFeature Name="{7a503555-4a83-11d1-a5db-00a0c90367f8}" />
          <AitFeature Name="{7b7166ec-21c7-44ae-b21a-c9ae321ae369}" />
          <AitFeature Name="{7bf80980-bf32-101a-8bbb-00aa00300cab}" />
          <AitFeature Name="{7bf80981-bf32-101a-8bbb-00aa00300cab}" />
          <AitFeature Name="{7c9dd65e-d3f7-4529-acee-785830acde35}" />
          <AitFeature Name="{7fd52380-4e07-101b-ae2d-08002b2ec713}" />
          <AitFeature Name="{80849279-c799-4797-8c33-0407a07d9e06}" />
          <AitFeature Name="{810b5013-e88d-11d2-8bc1-00600893b1b6}" />
          <AitFeature Name="{819074a2-016c-11d3-ae14-006097b01411}" />
          <AitFeature Name="{819074a3-016c-11d3-ae14-006097b01411}" />
          <AitFeature Name="{81bdcbca-64d4-426d-ae8d-ad0147f4275c}" />
          <AitFeature Name="{83783300-4063-4c8a-9db3-82830a7feb31}" />
          <AitFeature Name="{839d1216-bb2e-412b-b7f4-a9dbebe08ed1}" />
          <AitFeature Name="{84e63de0-46aa-11cf-816f-0000c020156e}" />
          <AitFeature Name="{85c31227-3de5-4f00-9b3a-f11ac38c18b5}" />
          <AitFeature Name="{86e0d1e0-8089-11d0-9ce4-08003e301f73}" />
          <AitFeature Name="{8767df22-bacc-11d1-8969-00a0c90629a8}" />
          <AitFeature Name="{87fc0268-9a55-4360-95aa-004a1d9de26c}" />
          <AitFeature Name="{880842e3-145f-43e6-a934-a71806e50547}" />
          <AitFeature Name="{881949a1-d6f3-11d0-89ab-00a0c9054129}" />
          <AitFeature Name="{894ad3b0-ef97-11ce-9bc9-00aa00608e01}" />
          <AitFeature Name="{89521360-aa8a-11cf-bfc7-444553540000}" />
          <AitFeature Name="{89521361-aa8a-11cf-bfc7-444553540000}" />
          <AitFeature Name="{89b2c488-4af4-11d1-8c4c-00c04fd930c5}" />
          <AitFeature Name="{8a667154-f9cb-11d2-ad8a-0060b0575abc}" />
          <AitFeature Name="{8aeeeac7-05f9-44d4-b591-000b0df1cb95}" />
          <AitFeature Name="{8ba5fb08-5195-40e2-ac58-0d989c3a0102}" />
          <AitFeature Name="{8bd28edf-50db-4e92-a2bd-445488d1ed42}" />
          <AitFeature Name="{8d19c834-8879-11d1-83e9-00c04fc2c6d4}" />
          <AitFeature Name="{8d536ca1-0cca-4956-a837-786963755584}" />
          <AitFeature Name="{8e5c6061-628a-4c8e-8264-bbe45cb3d5dd}" />
          <AitFeature Name="{8ecf4326-455f-4d8b-bda9-8d5d3e9e3e0b}" />
          <AitFeature Name="{903e9878-2c92-4072-9b2c-ea68f5396783}" />
          <AitFeature Name="{91886caf-1c3d-4d2e-a0ab-3e4c7d8d3303}" />
          <AitFeature Name="{922eada0-3424-11cf-b670-00aa004cd6d8}" />
          <AitFeature Name="{928c088b-76b9-4c6b-a536-a590853876cd}" />
          <AitFeature Name="{9301e380-1f22-11d3-8226-d2fa76255d47}" />
          <AitFeature Name="{93281500-8cf8-11d0-89ab-00a0c9054129}" />
          <AitFeature Name="{93281501-8cf8-11d0-89ab-00a0c9054129}" />
          <AitFeature Name="{93281502-8cf8-11d0-89ab-00a0c9054129}" />
          <AitFeature Name="{93281503-8cf8-11d0-89ab-00a0c9054129}" />
          <AitFeature Name="{934a9523-a3ca-4bc5-ada0-d6d95d979421}" />
          <AitFeature Name="{947990de-cc28-11d2-a0f7-00805f858fb1}" />
          <AitFeature Name="{94ea2b94-e9cc-49e0-c0ff-ee64ca8f5b90}" />
          <AitFeature Name="{9537ab04-3250-412e-8213-fcd2f8677933}" />
          <AitFeature Name="{969dc708-5c76-11d1-8d86-0000f804b057}" />
          <AitFeature Name="{995513af-3027-4b9a-956e-c772b3f78006}" />
          <AitFeature Name="{995c1cf5-54ff-11d3-8bda-00600893b1b6}" />
          <AitFeature Name="{99caf010-415e-11cf-8814-00aa00b569f5}" />
          <AitFeature Name="{9a4cb684-236d-11d3-8e9d-00c04f6844ae}" />
          <AitFeature Name="{9a4cb685-236d-11d3-8e9d-00c04f6844ae}" />
          <AitFeature Name="{9b32f9ad-bdcc-40a6-a39d-d5c865845720}" />
          <AitFeature Name="{9b7e4c00-342c-4106-a19f-4f2704f689f0}" />
          <AitFeature Name="{9b7e4c01-342c-4106-a19f-4f2704f689f0}" />
          <AitFeature Name="{9b7e4c02-342c-4106-a19f-4f2704f689f0}" />
          <AitFeature Name="{9b7e4c03-342c-4106-a19f-4f2704f689f0}" />
          <AitFeature Name="{9b7e4c04-342c-4106-a19f-4f2704f689f0}" />
          <AitFeature Name="{9b7e4c05-342c-4106-a19f-4f2704f689f0}" />
          <AitFeature Name="{9b7e4c07-342c-4106-a19f-4f2704f689f0}" />
          <AitFeature Name="{9b7e4c08-342c-4106-a19f-4f2704f689f0}" />
          <AitFeature Name="{9b7e4c09-342c-4106-a19f-4f2704f689f0}" />
          <AitFeature Name="{9b7e4c0a-342c-4106-a19f-4f2704f689f0}" />
          <AitFeature Name="{9b7e4c0b-342c-4106-a19f-4f2704f689f0}" />
          <AitFeature Name="{9b7e4c0c-342c-4106-a19f-4f2704f689f0}" />
          <AitFeature Name="{9b7e4c0d-342c-4106-a19f-4f2704f689f0}" />
          <AitFeature Name="{9b7e4c0e-342c-4106-a19f-4f2704f689f0}" />
          <AitFeature Name="{9b7e4c0f-342c-4106-a19f-4f2704f689f0}" />
          <AitFeature Name="{9b7e4c10-342c-4106-a19f-4f2704f689f0}" />
          <AitFeature Name="{9b7e4c11-342c-4106-a19f-4f2704f689f0}" />
          <AitFeature Name="{9b7e4c87-342c-4106-a19f-4f2704f689f0}" />
          <AitFeature Name="{9b7e4c8f-342c-4106-a19f-4f2704f689f0}" />
          <AitFeature Name="{9b7e4e00-342c-4106-a19f-4f2704f689f0}" />
          <AitFeature Name="{9b7e4e01-342c-4106-a19f-4f2704f689f0}" />
          <AitFeature Name="{9b7e4e02-342c-4106-a19f-4f2704f689f0}" />
          <AitFeature Name="{9bb4ab81-ab1a-4d8f-b506-fc04200b6ee7}" />
          <AitFeature Name="{9bfbbc02-eff1-101a-84ed-00aa00341d07}" />
          <AitFeature Name="{9c2cad80-3424-11cf-b670-00aa004cd6d8}" />
          <AitFeature Name="{9c59509a-39bd-11d1-8c4a-00c04fd930c5}" />
          <AitFeature Name="{9d460580-a822-11cf-960c-0080c7534e82}" />
          <AitFeature Name="{9d8e1289-d7b3-465f-8126-250e349af85d}" />
          <AitFeature Name="{9eb576dd-9f77-4d86-81aa-8bab5fe490e2}" />
          <AitFeature Name="{9fdac92a-1876-48c3-afad-25b94f84a9b6}" />
          <AitFeature Name="{a048285e-25a9-4527-bd93-d68b68c44254}" />
          <AitFeature Name="{a06eb39a-50da-425b-8c31-4eecd6c270f3}" />
          <AitFeature Name="{a158a630-ed6f-45fb-b987-f68676f57752}" />
          <AitFeature Name="{a1faf330-ef97-11ce-9bc9-00aa00608e01}" />
          <AitFeature Name="{a24bc4d1-769e-43f7-8013-98ff566c18e2}" />
          <AitFeature Name="{a2a07292-89af-4345-be2e-c53d9fbb6e9f}" />
          <AitFeature Name="{a2f05a09-27a2-42b5-bc0e-ac163ef49d9b}" />
          <AitFeature Name="{a39ee748-6a27-4817-a6f2-13914bef5890}" />
          <AitFeature Name="{a3e015b7-a82c-4dcd-a150-569aeeed36ab}" />
          <AitFeature Name="{a4665c60-2673-11cf-a31a-00aa00b93356}" />
          <AitFeature Name="{a4c23339-8e06-431e-9bf4-7e711c085648}" />
          <AitFeature Name="{a5029fb6-3c34-11d1-9c99-00c04fb998aa}" />
          <AitFeature Name="{a5ca5f7f-1847-4d87-9c5b-918509f7511d}" />
          <AitFeature Name="{a655fb94-0589-4e57-b333-567a89468c88}" />
          <AitFeature Name="{a6bc3ac0-dbaa-11ce-9de3-00aa004bb851}" />
          <AitFeature Name="{a6cd7faa-b0b7-4a2f-9436-8662a65797cb}" />
          <AitFeature Name="{a7aba9c1-8983-11cf-8f20-00805f2cd064}" />
          <AitFeature Name="{a9d758a0-4617-11cf-95fc-00aa00680db4}" />
          <AitFeature Name="{a9e213f2-9a60-486f-bf3b-53408b6d1cbb}" />
          <AitFeature Name="{aaa74ef9-8ee7-4659-88d9-f8c504da73cc}" />
          <AitFeature Name="{ad74143d-903d-4ab7-8066-28d363036d65}" />
          <AitFeature Name="{ae02eedb-c735-4690-8d52-5a8dc20213aa}" />
          <AitFeature Name="{ae897105-00e6-45bf-bb8e-281dd6db8e1b}" />
          <AitFeature Name="{aec22fb8-76f3-4639-9be0-28eb43a67a2e}" />
          <AitFeature Name="{af0ff408-129d-4b20-91f0-02bd23d88352}" />
          <AitFeature Name="{af465c71-9588-11cf-a020-00aa006157ac}" />
          <AitFeature Name="{af482368-330a-46a5-9a5c-01c71af24c8d}" />
          <AitFeature Name="{b0210780-89cd-11d0-af08-00a0c925cd16}" />
          <AitFeature Name="{b0210781-89cd-11d0-af08-00a0c925cd16}" />
          <AitFeature Name="{b0210782-89cd-11d0-af08-00a0c925cd16}" />
          <AitFeature Name="{b0210783-89cd-11d0-af08-00a0c925cd16}" />
          <AitFeature Name="{b07c4fe5-310d-4ba8-a23c-4f0f206f218b}" />
          <AitFeature Name="{b0ab3b60-33d7-11d1-a981-00c04fd7b174}" />
          <AitFeature Name="{b0ab3b61-33d7-11d1-a981-00c04fd7b174}" />
          <AitFeature Name="{b0e06fe0-8192-4e1a-b1ca-36d7414710b2}" />
          <AitFeature Name="{b15b8dc1-c7e1-11d0-8680-00aa00bdcb71}" />
          <AitFeature Name="{b18b10ce-2649-405a-870f-95f777d4313a}" />
          <AitFeature Name="{b196b283-bab4-101a-b69c-00aa00341d07}" />
          <AitFeature Name="{b196b284-bab4-101a-b69c-00aa00341d07}" />
          <AitFeature Name="{b196b285-bab4-101a-b69c-00aa00341d07}" />
          <AitFeature Name="{b196b286-bab4-101a-b69c-00aa00341d07}" />
          <AitFeature Name="{b196b287-bab4-101a-b69c-00aa00341d07}" />
          <AitFeature Name="{b196b288-bab4-101a-b69c-00aa00341d07}" />
          <AitFeature Name="{b196b289-bab4-101a-b69c-00aa00341d07}" />
          <AitFeature Name="{b196b28b-bab4-101a-b69c-00aa00341d07}" />
          <AitFeature Name="{b196b28c-bab4-101a-b69c-00aa00341d07}" />
          <AitFeature Name="{b196b28d-bab4-101a-b69c-00aa00341d07}" />
          <AitFeature Name="{b196b28f-bab4-101a-b69c-00aa00341d07}" />
          <AitFeature Name="{b36d93e0-2b43-11cf-a2de-00aa00b93356}" />
          <AitFeature Name="{b3a6f3e0-2b43-11cf-a2de-00aa00b93356}" />
          <AitFeature Name="{b3e7c340-ef97-11ce-9bc9-00aa00608e01}" />
          <AitFeature Name="{b4211cfa-51b9-4a9f-ab78-db99b2bb678e}" />
          <AitFeature Name="{b64bb1b5-fd70-4df6-bf91-19d0a12455e3}" />
          <AitFeature Name="{b96eebca-b326-4ea5-882f-2ff5bae021dd}" />
          <AitFeature Name="{b9dc4790-4af1-11d1-8c4c-00c04fd930c5}" />
          <AitFeature Name="{bae4d665-4ea1-11d3-8bda-00600893b1b6}" />
          <AitFeature Name="{bb223240-e72b-11d0-a9b4-00aa00c0993e}" />
          <AitFeature Name="{bc0bf6ae-8878-11d1-83e9-00c04fc2c6d4}" />
          <AitFeature Name="{bd1ae5e0-a6ae-11ce-bd37-504200c10000}" />
          <AitFeature Name="{bd7349f5-14f1-42e4-9c79-972380db40c0}" />
          <AitFeature Name="{bef6e002-a874-101a-8bba-00aa00300cab}" />
          <AitFeature Name="{bef6e003-a874-101a-8bba-00aa00300cab}" />
          <AitFeature Name="{bf798030-483a-4da2-aa99-5d64ed369700}" />
          <AitFeature Name="{bf798031-483a-4da2-aa99-5d64ed369700}" />
          <AitFeature Name="{bf963d80-c559-11d0-8a2b-00a0c9255ac1}" />
          <AitFeature Name="{c03c477e-6519-11d1-8c52-00c04fd930c5}" />
          <AitFeature Name="{c03ca9fe-fe90-4204-8078-82334cd177da}" />
          <AitFeature Name="{c03f6a43-65a4-9818-987e-e0b810d2a6f2}" />
          <AitFeature Name="{c0a7157b-d872-4b1d-8073-efc2acd4b1fc}" />
          <AitFeature Name="{c0bfa96c-e089-44fb-8eaf-26f8796190da}" />
          <AitFeature Name="{c2931aea-2a85-4f20-860f-fba1fd256e18}" />
          <AitFeature Name="{c3457783-a846-47ce-9520-cea6f66e7447}" />
          <AitFeature Name="{c4a54da0-e0af-11cf-9c4e-00a0c905425e}" />
          <AitFeature Name="{c50a7e93-f395-4834-9ef6-7fa99de50966}" />
          <AitFeature Name="{c530ad7d-9b16-4395-a979-ba2ecff83add}" />
          <AitFeature Name="{c7a98e66-1010-492c-a1c8-c809e1f75905}" />
          <AitFeature Name="{c902b03f-60a7-49ba-9936-2a3ab37a7e33}" />
          <AitFeature Name="{ca9c46f4-d3c5-11d1-b75a-00600852b312}" />
          <AitFeature Name="{cac701ee-80fc-4122-8242-10b39c8cec34}" />
          <AitFeature Name="{cafcb56c-6ac3-4889-bf47-9e23bbd260ec}" />
          <AitFeature Name="{cd45f185-1b21-48e2-967b-ead743a8914e}" />
          <AitFeature Name="{ced153e7-3606-11d2-b9f9-0000f875ac12}" />
          <AitFeature Name="{cf51ed10-62fe-11cf-bf86-00a0c9034836}" />
          <AitFeature Name="{d001f200-ef97-11ce-9bc9-00aa00608e01}" />
          <AitFeature Name="{d0223b96-bf7a-43fd-92bd-a43b0d82b9eb}" />
          <AitFeature Name="{d1eb6d20-8923-11d0-9d97-00a0c90a43cb}" />
          <AitFeature Name="{d2ac2878-b39b-11d1-8704-00600893b1bd}" />
          <AitFeature Name="{d2ac287a-b39b-11d1-8704-00600893b1bd}" />
          <AitFeature Name="{d2ac287b-b39b-11d1-8704-00600893b1bd}" />
          <AitFeature Name="{d2ac287c-b39b-11d1-8704-00600893b1bd}" />
          <AitFeature Name="{d2ac287d-b39b-11d1-8704-00600893b1bd}" />
          <AitFeature Name="{d2ac287e-b39b-11d1-8704-00600893b1bd}" />
          <AitFeature Name="{d2ac2881-b39b-11d1-8704-00600893b1bd}" />
          <AitFeature Name="{d2ac2882-b39b-11d1-8704-00600893b1bd}" />
          <AitFeature Name="{d2ac2883-b39b-11d1-8704-00600893b1bd}" />
          <AitFeature Name="{d2ac2884-b39b-11d1-8704-00600893b1bd}" />
          <AitFeature Name="{d2ac2885-b39b-11d1-8704-00600893b1bd}" />
          <AitFeature Name="{d2ac2886-b39b-11d1-8704-00600893b1bd}" />
          <AitFeature Name="{d2ac2887-b39b-11d1-8704-00600893b1bd}" />
          <AitFeature Name="{d2ac2888-b39b-11d1-8704-00600893b1bd}" />
          <AitFeature Name="{d2ac288a-b39b-11d1-8704-00600893b1bd}" />
          <AitFeature Name="{d2ac288b-b39b-11d1-8704-00600893b1bd}" />
          <AitFeature Name="{d2ac288c-b39b-11d1-8704-00600893b1bd}" />
          <AitFeature Name="{d2ac288d-b39b-11d1-8704-00600893b1bd}" />
          <AitFeature Name="{d2ac288e-b39b-11d1-8704-00600893b1bd}" />
          <AitFeature Name="{d2ac288f-b39b-11d1-8704-00600893b1bd}" />
          <AitFeature Name="{d2ac2890-b39b-11d1-8704-00600893b1bd}" />
          <AitFeature Name="{d2ac2892-b39b-11d1-8704-00600893b1bd}" />
          <AitFeature Name="{d2ac2894-b39b-11d1-8704-00600893b1bd}" />
          <AitFeature Name="{d2ac2896-b39b-11d1-8704-00600893b1bd}" />
          <AitFeature Name="{d2ac2897-b39b-11d1-8704-00600893b1bd}" />
          <AitFeature Name="{d2ac2898-b39b-11d1-8704-00600893b1bd}" />
          <AitFeature Name="{d40e20b6-f8f7-42ad-ab20-4baf8f15dfaa}" />
          <AitFeature Name="{d5f569d0-593b-101a-b569-08002b2dbf7a}" />
          <AitFeature Name="{d5f56a34-593b-101a-b569-08002b2dbf7a}" />
          <AitFeature Name="{d5f56afc-593b-101a-b569-08002b2dbf7a}" />
          <AitFeature Name="{d5f56b60-593b-101a-b569-08002b2dbf7a}" />
          <AitFeature Name="{d616f352-d622-11ce-aac5-0020af0b99a3}" />
          <AitFeature Name="{d6c00747-87b7-425e-b84d-44d108560afd}" />
          <AitFeature Name="{d7b70ee0-4340-11cf-b063-0020afc2cd35}" />
          <AitFeature Name="{d8f2f5e6-6102-4863-9f26-389a4676efde}" />
          <AitFeature Name="{d9771460-a695-4f26-bbd3-27b840b541cc}" />
          <AitFeature Name="{da044e00-69b2-11d0-a1d5-00aa00b8dfbb}" />
          <AitFeature Name="{da6fea51-564c-4487-9810-f0d0f9b4e3a5}" />
          <AitFeature Name="{da825e1b-6830-43d7-835d-0b5ad82956a2}" />
          <AitFeature Name="{dafd8210-5711-4b91-9fe3-f75b7ae279bf}" />
          <AitFeature Name="{db122ce8-d1c9-4292-b237-24ed3de8b175}" />
          <AitFeature Name="{db2f3aca-2f86-11d1-8e04-00c04fb9989a}" />
          <AitFeature Name="{db2f3acc-2f86-11d1-8e04-00c04fb9989a}" />
          <AitFeature Name="{db2f3ace-2f86-11d1-8e04-00c04fb9989a}" />
          <AitFeature Name="{db6f6ddb-ac77-4e88-8253-819df9bbf140}" />
          <AitFeature Name="{dc8e63f3-d12b-4952-b47b-5e45026a862d}" />
          <AitFeature Name="{dd13c59c-36fa-4098-a8fb-c7ed39dc8546}" />
          <AitFeature Name="{dd1ec3b3-8391-4fdb-a9e6-347c3caaa7dd}" />
          <AitFeature Name="{ddf57cba-9543-46e4-a12b-f207a0fe7fed}" />
          <AitFeature Name="{df0b3d60-548f-101b-8e65-08002b2bd119}" />
          <AitFeature Name="{dfdba067-0b8d-4865-875b-d7b4516cc164}" />
          <AitFeature Name="{e4819ddc-4cf0-4025-bd26-5de82a3e07b7}" />
          <AitFeature Name="{e4bcac13-7f99-4908-9a8e-74e3bf24b6e1}" />
          <AitFeature Name="{e4c1d9a2-cbf7-48bd-9a69-34a55e0d8941}" />
          <AitFeature Name="{e4cdd575-2866-4f01-b12e-7eece1ec9358}" />
          <AitFeature Name="{e5a0e990-2bad-430b-87da-a142cf75de58}" />
          <AitFeature Name="{e7e1f7c0-88d2-11d0-9ad0-00a0c9a06e35}" />
          <AitFeature Name="{e982ce48-0b96-440c-bc37-0c869b27a29e}" />
          <AitFeature Name="{ea82e40d-51dc-4f33-93d4-db7c9125ae8c}" />
          <AitFeature Name="{eb0cb9e8-7996-11d2-872e-0000f8080859}" />
          <AitFeature Name="{eb0d7dfa-1990-4f27-b4d6-edf2eec4a44c}" />
          <AitFeature Name="{eb62d63d-93dd-4318-8ae8-c6f83ad371b8}" />
          <AitFeature Name="{ebfe7ba0-628d-11d2-ae0f-006097b01411}" />
          <AitFeature Name="{ecc8691b-c1db-4dc0-855e-65f6c551af49}" />
          <AitFeature Name="{ed311e41-fbae-4175-9625-cd0854f693ca}" />
          <AitFeature Name="{edad8d19-8a35-4d6d-8566-2ea276cde161}" />
          <AitFeature Name="{edad8d99-8a35-4d6d-8566-2ea276cde161}" />
          <AitFeature Name="{edc17559-dd5d-4846-8eef-8becba5a4abf}" />
          <AitFeature Name="{edcb4c7a-daab-4216-a42e-6c50596ddc1d}" />
          <AitFeature Name="{ee0b9ca0-a81e-11d3-9bd1-0080c7150a74}" />
          <AitFeature Name="{eec6993a-b3fd-11d2-a916-00c04fb98638}" />
          <AitFeature Name="{eed36461-9ea5-11d3-9bd1-0080c7150a74}" />
          <AitFeature Name="{ef011f79-4000-406d-87af-bffb3fc39d57}" />
          <AitFeature Name="{ef114c90-cd1d-484e-96e5-09cfaf912a21}" />
          <AitFeature Name="{ef3e932c-d40b-4f51-8ccf-3f98f1b29d5d}" />
          <AitFeature Name="{ef985e71-d5c7-42d4-ba4d-2d073e2e96f4}" />
          <AitFeature Name="{efc5557e-6265-4613-8a94-43857889eb36}" />
          <AitFeature Name="{efca3d92-dfd8-4672-a603-7420894bad98}" />
          <AitFeature Name="{efe6629c-81f7-4281-bd91-c9d604a95af6}" />
          <AitFeature Name="{f134c4b7-b1f8-4e75-b886-74b90943becb}" />
          <AitFeature Name="{f164edf1-cc7c-4f0d-9a94-34222625c393}" />
          <AitFeature Name="{f17e8672-c3b4-11d1-870b-00600893b1bd}" />
          <AitFeature Name="{f1e50292-a795-4117-8e09-2b560a72ac60}" />
          <AitFeature Name="{f2086b20-259f-11cf-a31a-00aa00b93356}" />
          <AitFeature Name="{f286fa56-c1fd-4270-8e67-b3eb790a81e8}" />
          <AitFeature Name="{f29f6bc0-5021-11ce-aa15-00006901293f}" />
          <AitFeature Name="{f2f0ce00-e0af-11cf-9c4e-00a0c905425e}" />
          <AitFeature Name="{f5049e77-4861-11d2-a407-00a0c90629a8}" />
          <AitFeature Name="{f5049e78-4861-11d2-a407-00a0c90629a8}" />
          <AitFeature Name="{f5049e79-4861-11d2-a407-00a0c90629a8}" />
          <AitFeature Name="{f5049e7d-4861-11d2-a407-00a0c90629a8}" />
          <AitFeature Name="{f5185dd8-2012-4b0b-aad9-f052c6bd482b}" />
          <AitFeature Name="{f582c508-0f36-490c-9977-31eece268cfa}" />
          <AitFeature Name="{f8fb5c27-c6b3-4f75-a4c8-439af2ef564c}" />
          <AitFeature Name="{fc47060e-6153-4b34-b975-8e4121eb7f3c}" />
          <AitFeature Name="{fc4801a1-2ba9-11cf-a229-00aa003d7352}" />
          <AitFeature Name="{fc4801a3-2ba9-11cf-a229-00aa003d7352}" />
          <AitFeature Name="{fea4300c-7959-4147-b26a-2377b9e7a91d}" />
          <AitFeature Name="{fff32f81-d953-473a-9223-93d652aba93f}" />
        </AitCategory>
        <AitCategory Id="ApiStatic">
          <AitFeature Name="gdi32.dll!BitBlt" />
          <AitFeature Name="gdi32.dll!ChoosePixelFormat" />
          <AitFeature Name="gdi32.dll!CreateCompatibleBitmap" />
          <AitFeature Name="gdi32.dll!CreateCompatibleDC" />
          <AitFeature Name="gdi32.dll!CreateDIBSection" />
          <AitFeature Name="gdi32.dll!CreatePalette" />
          <AitFeature Name="gdi32.dll!DeleteDC" />
          <AitFeature Name="gdi32.dll!DeleteObject" />
          <AitFeature Name="gdi32.dll!DescribePixelFormat" />
          <AitFeature Name="gdi32.dll!GetDIBits" />
          <AitFeature Name="gdi32.dll!GetDeviceCaps" />
          <AitFeature Name="gdi32.dll!GetDeviceGammaRamp" />
          <AitFeature Name="gdi32.dll!GetSystemPaletteEntries" />
          <AitFeature Name="gdi32.dll!GetSystemPaletteUse" />
          <AitFeature Name="gdi32.dll!RealizePalette" />
          <AitFeature Name="gdi32.dll!SelectObject" />
          <AitFeature Name="gdi32.dll!SelectPalette" />
          <AitFeature Name="gdi32.dll!SetDIBColorTable" />
          <AitFeature Name="gdi32.dll!SetDeviceGammaRamp" />
          <AitFeature Name="gdi32.dll!SetPaletteEntries" />
          <AitFeature Name="gdi32.dll!SetPixelFormat" />
          <AitFeature Name="gdi32.dll!SetSystemPaletteUse" />
          <AitFeature Name="gdi32.dll!SwapBuffers" />
          <AitFeature Name="gdi32.dll!UnrealizeObject" />
          <AitFeature Name="advapi32.dll!RegCloseKey" />
          <AitFeature Name="advapi32.dll!RegOpenKeyExA" />
          <AitFeature Name="advapi32.dll!RegQueryValueExA" />
          <AitFeature Name="kernel32.dll!CloseHandle" />
          <AitFeature Name="kernel32.dll!CreateEventA" />
          <AitFeature Name="kernel32.dll!CreateFileA" />
          <AitFeature Name="kernel32.dll!CreateFileW" />
          <AitFeature Name="kernel32.dll!CreateMutexA" />
          <AitFeature Name="kernel32.dll!CreateSemaphoreA" />
          <AitFeature Name="kernel32.dll!DeleteCriticalSection" />
          <AitFeature Name="kernel32.dll!EnterCriticalSection" />
          <AitFeature Name="kernel32.dll!FormatMessageA" />
          <AitFeature Name="kernel32.dll!FreeLibrary" />
          <AitFeature Name="kernel32.dll!GetCurrentThread" />
          <AitFeature Name="kernel32.dll!GetCurrentThreadId" />
          <AitFeature Name="kernel32.dll!GetDriveTypeA" />
          <AitFeature Name="kernel32.dll!GetEnvironmentVariableA" />
          <AitFeature Name="kernel32.dll!GetLastError" />
          <AitFeature Name="kernel32.dll!GetModuleHandleA" />
          <AitFeature Name="kernel32.dll!GetProcAddress" />
          <AitFeature Name="kernel32.dll!GetVersionExA" />
          <AitFeature Name="kernel32.dll!InitializeCriticalSection" />
          <AitFeature Name="kernel32.dll!IsDBCSLeadByteEx" />
          <AitFeature Name="kernel32.dll!LeaveCriticalSection" />
          <AitFeature Name="kernel32.dll!LoadLibraryA" />
          <AitFeature Name="kernel32.dll!MultiByteToWideChar" />
          <AitFeature Name="kernel32.dll!QueryPerformanceCounter" />
          <AitFeature Name="kernel32.dll!ReadFile" />
          <AitFeature Name="kernel32.dll!ReleaseMutex" />
          <AitFeature Name="kernel32.dll!ReleaseSemaphore" />
          <AitFeature Name="kernel32.dll!SetEnvironmentVariableA" />
          <AitFeature Name="kernel32.dll!SetErrorMode" />
          <AitFeature Name="kernel32.dll!SetFilePointer" />
          <AitFeature Name="kernel32.dll!SetThreadPriority" />
          <AitFeature Name="kernel32.dll!Sleep" />
          <AitFeature Name="kernel32.dll!TerminateThread" />
          <AitFeature Name="kernel32.dll!TlsGetValue" />
          <AitFeature Name="kernel32.dll!VirtualProtect" />
          <AitFeature Name="kernel32.dll!VirtualQuery" />
          <AitFeature Name="kernel32.dll!WaitForSingleObject" />
          <AitFeature Name="kernel32.dll!WideCharToMultiByte" />
          <AitFeature Name="kernel32.dll!WriteFile" />
          <AitFeature Name="user32.dll!AdjustWindowRect" />
          <AitFeature Name="user32.dll!AdjustWindowRectEx" />
          <AitFeature Name="user32.dll!BeginPaint" />
          <AitFeature Name="user32.dll!CallWindowProcA" />
          <AitFeature Name="user32.dll!ChangeDisplaySettingsA" />
          <AitFeature Name="user32.dll!ClientToScreen" />
          <AitFeature Name="user32.dll!ClipCursor" />
          <AitFeature Name="user32.dll!CreateCursor" />
          <AitFeature Name="user32.dll!CreateIconFromResourceEx" />
          <AitFeature Name="user32.dll!CreateWindowExA" />
          <AitFeature Name="user32.dll!DefWindowProcA" />
          <AitFeature Name="user32.dll!DestroyCursor" />
          <AitFeature Name="user32.dll!DestroyIcon" />
          <AitFeature Name="user32.dll!DestroyWindow" />
          <AitFeature Name="user32.dll!DispatchMessageA" />
          <AitFeature Name="user32.dll!EndPaint" />
          <AitFeature Name="user32.dll!EnumDisplaySettingsA" />
          <AitFeature Name="user32.dll!GetClassInfoA" />
          <AitFeature Name="user32.dll!GetClientRect" />
          <AitFeature Name="user32.dll!GetCursor" />
          <AitFeature Name="user32.dll!GetCursorPos" />
          <AitFeature Name="user32.dll!GetDC" />
          <AitFeature Name="user32.dll!GetDesktopWindow" />
          <AitFeature Name="user32.dll!GetForegroundWindow" />
          <AitFeature Name="user32.dll!GetKeyState" />
          <AitFeature Name="user32.dll!GetKeyboardLayout" />
          <AitFeature Name="user32.dll!GetKeyboardLayoutNameA" />
          <AitFeature Name="user32.dll!GetKeyboardState" />
          <AitFeature Name="user32.dll!GetMenu" />
          <AitFeature Name="user32.dll!GetMessageA" />
          <AitFeature Name="user32.dll!GetParent" />
          <AitFeature Name="user32.dll!GetSystemMetrics" />
          <AitFeature Name="user32.dll!GetWindowLongA" />
          <AitFeature Name="user32.dll!GetWindowLongPtrA" />
          <AitFeature Name="user32.dll!GetWindowRect" />
          <AitFeature Name="user32.dll!InvalidateRect" />
          <AitFeature Name="user32.dll!IsZoomed" />
          <AitFeature Name="user32.dll!KillTimer" />
          <AitFeature Name="user32.dll!LoadImageA" />
          <AitFeature Name="user32.dll!LoadKeyboardLayoutA" />
          <AitFeature Name="user32.dll!MapVirtualKeyA" />
          <AitFeature Name="user32.dll!MapVirtualKeyExA" />
          <AitFeature Name="user32.dll!MapWindowPoints" />
          <AitFeature Name="user32.dll!MsgWaitForMultipleObjects" />
          <AitFeature Name="user32.dll!PeekMessageA" />
          <AitFeature Name="user32.dll!PostMessageA" />
          <AitFeature Name="user32.dll!PostQuitMessage" />
          <AitFeature Name="user32.dll!PtInRect" />
          <AitFeature Name="user32.dll!RegisterClassA" />
          <AitFeature Name="user32.dll!ReleaseCapture" />
          <AitFeature Name="user32.dll!ReleaseDC" />
          <AitFeature Name="user32.dll!ScreenToClient" />
          <AitFeature Name="user32.dll!SetCapture" />
          <AitFeature Name="user32.dll!SetClassLongPtrA" />
          <AitFeature Name="user32.dll!SetCursor" />
          <AitFeature Name="user32.dll!SetCursorPos" />
          <AitFeature Name="user32.dll!SetFocus" />
          <AitFeature Name="user32.dll!SetForegroundWindow" />
          <AitFeature Name="user32.dll!SetTimer" />
          <AitFeature Name="user32.dll!SetWindowLongA" />
          <AitFeature Name="user32.dll!SetWindowLongPtrA" />
          <AitFeature Name="user32.dll!SetWindowPos" />
          <AitFeature Name="user32.dll!SetWindowTextA" />
          <AitFeature Name="user32.dll!ShowWindow" />
          <AitFeature Name="user32.dll!ToUnicode" />
          <AitFeature Name="user32.dll!TranslateMessage" />
          <AitFeature Name="user32.dll!UnregisterClassA" />
          <AitFeature Name="user32.dll!WindowFromPoint" />
          <AitFeature Name="winmm.dll!joyGetDevCapsA" />
          <AitFeature Name="winmm.dll!joyGetNumDevs" />
          <AitFeature Name="winmm.dll!joyGetPosEx" />
          <AitFeature Name="winmm.dll!mciGetErrorStringA" />
          <AitFeature Name="winmm.dll!mciSendCommandA" />
          <AitFeature Name="winmm.dll!timeBeginPeriod" />
          <AitFeature Name="winmm.dll!timeEndPeriod" />
          <AitFeature Name="winmm.dll!timeGetTime" />
          <AitFeature Name="winmm.dll!timeKillEvent" />
          <AitFeature Name="winmm.dll!timeSetEvent" />
          <AitFeature Name="winmm.dll!waveOutClose" />
          <AitFeature Name="winmm.dll!waveOutGetErrorTextA" />
          <AitFeature Name="winmm.dll!waveOutOpen" />
          <AitFeature Name="winmm.dll!waveOutPrepareHeader" />
          <AitFeature Name="winmm.dll!waveOutUnprepareHeader" />
          <AitFeature Name="winmm.dll!waveOutWrite" />
          <AitFeature Name="msvcrt.dll!___lc_codepage_func" />
          <AitFeature Name="msvcrt.dll!___mb_cur_max_func" />
          <AitFeature Name="msvcrt.dll!__iob_func" />
          <AitFeature Name="msvcrt.dll!__setusermatherr" />
          <AitFeature Name="msvcrt.dll!_amsg_exit" />
          <AitFeature Name="msvcrt.dll!_beginthreadex" />
          <AitFeature Name="msvcrt.dll!_endthreadex" />
          <AitFeature Name="msvcrt.dll!_errno" />
          <AitFeature Name="msvcrt.dll!_initterm" />
          <AitFeature Name="msvcrt.dll!_lock" />
          <AitFeature Name="msvcrt.dll!_strdup" />
          <AitFeature Name="msvcrt.dll!_stricmp" />
          <AitFeature Name="msvcrt.dll!_unlock" />
          <AitFeature Name="msvcrt.dll!abort" />
          <AitFeature Name="msvcrt.dll!atof" />
          <AitFeature Name="msvcrt.dll!atoi" />
          <AitFeature Name="msvcrt.dll!calloc" />
          <AitFeature Name="msvcrt.dll!fclose" />
          <AitFeature Name="msvcrt.dll!ferror" />
          <AitFeature Name="msvcrt.dll!fputc" />
          <AitFeature Name="msvcrt.dll!fread" />
          <AitFeature Name="msvcrt.dll!free" />
          <AitFeature Name="msvcrt.dll!fseek" />
          <AitFeature Name="msvcrt.dll!ftell" />
          <AitFeature Name="msvcrt.dll!fwrite" />
          <AitFeature Name="msvcrt.dll!getc" />
          <AitFeature Name="msvcrt.dll!islower" />
          <AitFeature Name="msvcrt.dll!isspace" />
          <AitFeature Name="msvcrt.dll!isupper" />
          <AitFeature Name="msvcrt.dll!isxdigit" />
          <AitFeature Name="msvcrt.dll!localeconv" />
          <AitFeature Name="msvcrt.dll!malloc" />
          <AitFeature Name="msvcrt.dll!memcmp" />
          <AitFeature Name="msvcrt.dll!memcpy" />
          <AitFeature Name="msvcrt.dll!memmove" />
          <AitFeature Name="msvcrt.dll!memset" />
          <AitFeature Name="msvcrt.dll!qsort" />
          <AitFeature Name="msvcrt.dll!raise" />
          <AitFeature Name="msvcrt.dll!realloc" />
          <AitFeature Name="msvcrt.dll!signal" />
          <AitFeature Name="msvcrt.dll!strchr" />
          <AitFeature Name="msvcrt.dll!strcmp" />
          <AitFeature Name="msvcrt.dll!strerror" />
          <AitFeature Name="msvcrt.dll!strlen" />
          <AitFeature Name="msvcrt.dll!strncmp" />
          <AitFeature Name="msvcrt.dll!strstr" />
          <AitFeature Name="msvcrt.dll!strtol" />
          <AitFeature Name="msvcrt.dll!strtoul" />
          <AitFeature Name="msvcrt.dll!tolower" />
          <AitFeature Name="msvcrt.dll!ungetc" />
          <AitFeature Name="msvcrt.dll!vfprintf" />
          <AitFeature Name="msvcrt.dll!wcslen" />
        </AitCategory>
        <AitCategory Id="ApiDynamic">
          <AitFeature Name="opengl32.dll!glBegin" />
          <AitFeature Name="opengl32.dll!glBindTexture" />
          <AitFeature Name="opengl32.dll!glBlendFunc" />
          <AitFeature Name="opengl32.dll!glColor4f" />
          <AitFeature Name="opengl32.dll!glDisable" />
          <AitFeature Name="opengl32.dll!glEnable" />
          <AitFeature Name="opengl32.dll!glEnd" />
          <AitFeature Name="opengl32.dll!glFlush" />
          <AitFeature Name="opengl32.dll!glGenTextures" />
          <AitFeature Name="opengl32.dll!glGetString" />
          <AitFeature Name="opengl32.dll!glLoadIdentity" />
          <AitFeature Name="opengl32.dll!glMatrixMode" />
          <AitFeature Name="opengl32.dll!glOrtho" />
          <AitFeature Name="opengl32.dll!glPixelStorei" />
          <AitFeature Name="opengl32.dll!glPopAttrib" />
          <AitFeature Name="opengl32.dll!glPopClientAttrib" />
          <AitFeature Name="opengl32.dll!glPopMatrix" />
          <AitFeature Name="opengl32.dll!glPushAttrib" />
          <AitFeature Name="opengl32.dll!glPushClientAttrib" />
          <AitFeature Name="opengl32.dll!glPushMatrix" />
          <AitFeature Name="opengl32.dll!glTexCoord2f" />
          <AitFeature Name="opengl32.dll!glTexEnvf" />
          <AitFeature Name="opengl32.dll!glTexImage2D" />
          <AitFeature Name="opengl32.dll!glTexParameteri" />
          <AitFeature Name="opengl32.dll!glTexSubImage2D" />
          <AitFeature Name="opengl32.dll!glVertex2i" />
          <AitFeature Name="opengl32.dll!glViewport" />
          <AitFeature Name="opengl32.dll!wglCreateContext" />
          <AitFeature Name="opengl32.dll!wglDeleteContext" />
          <AitFeature Name="opengl32.dll!wglGetProcAddress" />
          <AitFeature Name="opengl32.dll!wglMakeCurrent" />
          <AitFeature Name="user32.dll!TrackMouseEvent" />
          <AitFeature Name="dsound.dll!DirectSoundCaptureCreate" />
          <AitFeature Name="dsound.dll!DirectSoundCreate" />
          <AitFeature Name="msvcrt.dll!log" />
          <AitFeature Name="msvcrt.dll!pow" />
          <AitFeature Name="dinput.dll!DirectInputCreateA" />
          <AitFeature Name="ddraw.dll!DirectDrawCreate" />
        </AitCategory>
      </AitFile>
      <AitFile ErrorCode="0" Name="schismtracker.exe" Id="0000aee622d235de77f235e801c688e70e512f013eee">
        <AitCategory Id="Com">
          <AitFeature Name="{00000000-0000-0000-0000-000000000001}" />
          <AitFeature Name="{00000000-0000-0000-0000-000000000002}" />
          <AitFeature Name="{00000000-0000-0000-0000-000000000003}" />
          <AitFeature Name="{00000000-0000-0000-0000-000000000006}" />
          <AitFeature Name="{00000000-0000-0000-0000-000000000007}" />
          <AitFeature Name="{00000000-0000-0000-0000-000000000009}" />
          <AitFeature Name="{00000000-0000-0000-0000-000000000010}" />
          <AitFeature Name="{00000000-0000-0000-0000-000000000012}" />
          <AitFeature Name="{00000000-0000-0000-0000-000000000013}" />
          <AitFeature Name="{00000000-0000-0000-0000-000000000014}" />
          <AitFeature Name="{00000000-0000-0000-0000-000000000015}" />
          <AitFeature Name="{00000000-0000-0000-0000-000000000017}" />
          <AitFeature Name="{00000000-0000-0000-0000-000000000018}" />
          <AitFeature Name="{00000000-0000-0000-0000-000000000021}" />
          <AitFeature Name="{00000000-0000-0000-0000-000000000024}" />
          <AitFeature Name="{00000000-0000-0000-0000-000000000027}" />
          <AitFeature Name="{10000000-0000-0000-0000-000000000001}" />
        </AitCategory>
        <AitCategory Id="ApiStatic">
          <AitFeature Name="wsock32.dll!WSACleanup" />
          <AitFeature Name="wsock32.dll!WSAGetLastError" />
          <AitFeature Name="wsock32.dll!WSAStartup" />
          <AitFeature Name="wsock32.dll!__WSAFDIsSet" />
          <AitFeature Name="wsock32.dll!bind" />
          <AitFeature Name="wsock32.dll!closesocket" />
          <AitFeature Name="wsock32.dll!htons" />
          <AitFeature Name="wsock32.dll!recvfrom" />
          <AitFeature Name="wsock32.dll!select" />
          <AitFeature Name="wsock32.dll!sendto" />
          <AitFeature Name="wsock32.dll!setsockopt" />
          <AitFeature Name="wsock32.dll!socket" />
          <AitFeature Name="kernel32.dll!CloseHandle" />
          <AitFeature Name="kernel32.dll!CreateFileA" />
          <AitFeature Name="kernel32.dll!CreateFileMappingA" />
          <AitFeature Name="kernel32.dll!DeleteCriticalSection" />
          <AitFeature Name="kernel32.dll!DeleteFileA" />
          <AitFeature Name="kernel32.dll!EnterCriticalSection" />
          <AitFeature Name="kernel32.dll!FormatMessageA" />
          <AitFeature Name="kernel32.dll!FreeLibrary" />
          <AitFeature Name="kernel32.dll!GetCommandLineA" />
          <AitFeature Name="kernel32.dll!GetCurrentDirectoryA" />
          <AitFeature Name="kernel32.dll!GetCurrentProcess" />
          <AitFeature Name="kernel32.dll!GetCurrentThread" />
          <AitFeature Name="kernel32.dll!GetEnvironmentVariableW" />
          <AitFeature Name="kernel32.dll!GetFileAttributesA" />
          <AitFeature Name="kernel32.dll!GetLastError" />
          <AitFeature Name="kernel32.dll!GetLogicalDrives" />
          <AitFeature Name="kernel32.dll!GetModuleFileNameA" />
          <AitFeature Name="kernel32.dll!GetModuleHandleA" />
          <AitFeature Name="kernel32.dll!GetProcAddress" />
          <AitFeature Name="kernel32.dll!GetStartupInfoA" />
          <AitFeature Name="kernel32.dll!GetSystemTimeAsFileTime" />
          <AitFeature Name="kernel32.dll!GetTimeZoneInformation" />
          <AitFeature Name="kernel32.dll!GlobalAlloc" />
          <AitFeature Name="kernel32.dll!GlobalLock" />
          <AitFeature Name="kernel32.dll!GlobalSize" />
          <AitFeature Name="kernel32.dll!GlobalUnlock" />
          <AitFeature Name="kernel32.dll!InitializeCriticalSection" />
          <AitFeature Name="kernel32.dll!IsDBCSLeadByteEx" />
          <AitFeature Name="kernel32.dll!LeaveCriticalSection" />
          <AitFeature Name="kernel32.dll!LoadLibraryA" />
          <AitFeature Name="kernel32.dll!LocalFree" />
          <AitFeature Name="kernel32.dll!MapViewOfFile" />
          <AitFeature Name="kernel32.dll!MoveFileA" />
          <AitFeature Name="kernel32.dll!MoveFileExA" />
          <AitFeature Name="kernel32.dll!MultiByteToWideChar" />
          <AitFeature Name="kernel32.dll!SetCurrentDirectoryA" />
          <AitFeature Name="kernel32.dll!SetErrorMode" />
          <AitFeature Name="kernel32.dll!SetFileAttributesA" />
          <AitFeature Name="kernel32.dll!SetPriorityClass" />
          <AitFeature Name="kernel32.dll!SetThreadPriority" />
          <AitFeature Name="kernel32.dll!SetUnhandledExceptionFilter" />
          <AitFeature Name="kernel32.dll!Sleep" />
          <AitFeature Name="kernel32.dll!SleepEx" />
          <AitFeature Name="kernel32.dll!TlsGetValue" />
          <AitFeature Name="kernel32.dll!UnmapViewOfFile" />
          <AitFeature Name="kernel32.dll!VirtualProtect" />
          <AitFeature Name="kernel32.dll!VirtualQuery" />
          <AitFeature Name="kernel32.dll!WideCharToMultiByte" />
          <AitFeature Name="shell32.dll!SHChangeNotify" />
          <AitFeature Name="shell32.dll!SHGetFolderPathA" />
          <AitFeature Name="user32.dll!ActivateKeyboardLayout" />
          <AitFeature Name="user32.dll!CloseClipboard" />
          <AitFeature Name="user32.dll!EmptyClipboard" />
          <AitFeature Name="user32.dll!GetClipboardData" />
          <AitFeature Name="user32.dll!GetKeyboardLayout" />
          <AitFeature Name="user32.dll!GetKeyboardState" />
          <AitFeature Name="user32.dll!IsClipboardFormatAvailable" />
          <AitFeature Name="user32.dll!LoadKeyboardLayoutA" />
          <AitFeature Name="user32.dll!MapVirtualKeyExA" />
          <AitFeature Name="user32.dll!OpenClipboard" />
          <AitFeature Name="user32.dll!SetClipboardData" />
          <AitFeature Name="user32.dll!SystemParametersInfoA" />
          <AitFeature Name="winmm.dll!midiInAddBuffer" />
          <AitFeature Name="winmm.dll!midiInClose" />
          <AitFeature Name="winmm.dll!midiInGetDevCapsA" />
          <AitFeature Name="winmm.dll!midiInGetNumDevs" />
          <AitFeature Name="winmm.dll!midiInOpen" />
          <AitFeature Name="winmm.dll!midiInPrepareHeader" />
          <AitFeature Name="winmm.dll!midiInReset" />
          <AitFeature Name="winmm.dll!midiInStart" />
          <AitFeature Name="winmm.dll!midiInStop" />
          <AitFeature Name="winmm.dll!midiInUnprepareHeader" />
          <AitFeature Name="winmm.dll!midiOutClose" />
          <AitFeature Name="winmm.dll!midiOutGetDevCapsA" />
          <AitFeature Name="winmm.dll!midiOutGetNumDevs" />
          <AitFeature Name="winmm.dll!midiOutLongMsg" />
          <AitFeature Name="winmm.dll!midiOutOpen" />
          <AitFeature Name="winmm.dll!midiOutPrepareHeader" />
          <AitFeature Name="winmm.dll!midiOutReset" />
          <AitFeature Name="winmm.dll!midiOutShortMsg" />
          <AitFeature Name="winmm.dll!timeBeginPeriod" />
          <AitFeature Name="winmm.dll!timeGetDevCaps" />
          <AitFeature Name="winmm.dll!timeSetEvent" />
          <AitFeature Name="winmm.dll!waveOutGetVolume" />
          <AitFeature Name="winmm.dll!waveOutSetVolume" />
          <AitFeature Name="msvcrt.dll!__C_specific_handler" />
          <AitFeature Name="msvcrt.dll!___lc_codepage_func" />
          <AitFeature Name="msvcrt.dll!___mb_cur_max_func" />
          <AitFeature Name="msvcrt.dll!__argv" />
          <AitFeature Name="msvcrt.dll!__getmainargs" />
          <AitFeature Name="msvcrt.dll!__initenv" />
          <AitFeature Name="msvcrt.dll!__iob_func" />
          <AitFeature Name="msvcrt.dll!__set_app_type" />
          <AitFeature Name="msvcrt.dll!__setusermatherr" />
          <AitFeature Name="msvcrt.dll!_access" />
          <AitFeature Name="msvcrt.dll!_acmdln" />
          <AitFeature Name="msvcrt.dll!_amsg_exit" />
          <AitFeature Name="msvcrt.dll!_assert" />
          <AitFeature Name="msvcrt.dll!_cexit" />
          <AitFeature Name="msvcrt.dll!_chdir" />
          <AitFeature Name="msvcrt.dll!_chmod" />
          <AitFeature Name="msvcrt.dll!_close" />
          <AitFeature Name="msvcrt.dll!_commode" />
          <AitFeature Name="msvcrt.dll!_dup" />
          <AitFeature Name="msvcrt.dll!_errno" />
          <AitFeature Name="msvcrt.dll!_fdopen" />
          <AitFeature Name="msvcrt.dll!_findclose" />
          <AitFeature Name="msvcrt.dll!_findfirst64" />
          <AitFeature Name="msvcrt.dll!_findnext64" />
          <AitFeature Name="msvcrt.dll!_fmode" />
          <AitFeature Name="msvcrt.dll!_fullpath" />
          <AitFeature Name="msvcrt.dll!_getcwd" />
          <AitFeature Name="msvcrt.dll!_initterm" />
          <AitFeature Name="msvcrt.dll!_isctype" />
          <AitFeature Name="msvcrt.dll!_localtime64" />
          <AitFeature Name="msvcrt.dll!_lock" />
          <AitFeature Name="msvcrt.dll!_mkdir" />
          <AitFeature Name="msvcrt.dll!_mktime64" />
          <AitFeature Name="msvcrt.dll!_onexit" />
          <AitFeature Name="msvcrt.dll!_open" />
          <AitFeature Name="msvcrt.dll!_putenv" />
          <AitFeature Name="msvcrt.dll!_sopen" />
          <AitFeature Name="msvcrt.dll!_spawnlp" />
          <AitFeature Name="msvcrt.dll!_stat64" />
          <AitFeature Name="msvcrt.dll!_strdup" />
          <AitFeature Name="msvcrt.dll!_stricmp" />
          <AitFeature Name="msvcrt.dll!_strnicmp" />
          <AitFeature Name="msvcrt.dll!_time64" />
          <AitFeature Name="msvcrt.dll!_tzset" />
          <AitFeature Name="msvcrt.dll!_umask" />
          <AitFeature Name="msvcrt.dll!_unlink" />
          <AitFeature Name="msvcrt.dll!_unlock" />
          <AitFeature Name="msvcrt.dll!abort" />
          <AitFeature Name="msvcrt.dll!atoi" />
          <AitFeature Name="msvcrt.dll!calloc" />
          <AitFeature Name="msvcrt.dll!exit" />
          <AitFeature Name="msvcrt.dll!fclose" />
          <AitFeature Name="msvcrt.dll!feof" />
          <AitFeature Name="msvcrt.dll!ferror" />
          <AitFeature Name="msvcrt.dll!fgetc" />
          <AitFeature Name="msvcrt.dll!fopen" />
          <AitFeature Name="msvcrt.dll!fprintf" />
          <AitFeature Name="msvcrt.dll!fputc" />
          <AitFeature Name="msvcrt.dll!fread" />
          <AitFeature Name="msvcrt.dll!free" />
          <AitFeature Name="msvcrt.dll!freopen" />
          <AitFeature Name="msvcrt.dll!fseek" />
          <AitFeature Name="msvcrt.dll!ftell" />
          <AitFeature Name="msvcrt.dll!fwrite" />
          <AitFeature Name="msvcrt.dll!getc" />
          <AitFeature Name="msvcrt.dll!getenv" />
          <AitFeature Name="msvcrt.dll!isalpha" />
          <AitFeature Name="msvcrt.dll!islower" />
          <AitFeature Name="msvcrt.dll!isspace" />
          <AitFeature Name="msvcrt.dll!isupper" />
          <AitFeature Name="msvcrt.dll!isxdigit" />
          <AitFeature Name="msvcrt.dll!localeconv" />
          <AitFeature Name="msvcrt.dll!log10" />
          <AitFeature Name="msvcrt.dll!malloc" />
          <AitFeature Name="msvcrt.dll!memchr" />
          <AitFeature Name="msvcrt.dll!memcmp" />
          <AitFeature Name="msvcrt.dll!memcpy" />
          <AitFeature Name="msvcrt.dll!memmove" />
          <AitFeature Name="msvcrt.dll!memset" />
          <AitFeature Name="msvcrt.dll!perror" />
          <AitFeature Name="msvcrt.dll!puts" />
          <AitFeature Name="msvcrt.dll!qsort" />
          <AitFeature Name="msvcrt.dll!rand" />
          <AitFeature Name="msvcrt.dll!realloc" />
          <AitFeature Name="msvcrt.dll!remove" />
          <AitFeature Name="msvcrt.dll!rewind" />
          <AitFeature Name="msvcrt.dll!setbuf" />
          <AitFeature Name="msvcrt.dll!setvbuf" />
          <AitFeature Name="msvcrt.dll!signal" />
          <AitFeature Name="msvcrt.dll!srand" />
          <AitFeature Name="msvcrt.dll!strcat" />
          <AitFeature Name="msvcrt.dll!strchr" />
          <AitFeature Name="msvcrt.dll!strcmp" />
          <AitFeature Name="msvcrt.dll!strcpy" />
          <AitFeature Name="msvcrt.dll!strcspn" />
          <AitFeature Name="msvcrt.dll!strerror" />
          <AitFeature Name="msvcrt.dll!strlen" />
          <AitFeature Name="msvcrt.dll!strncmp" />
          <AitFeature Name="msvcrt.dll!strncpy" />
          <AitFeature Name="msvcrt.dll!strpbrk" />
          <AitFeature Name="msvcrt.dll!strrchr" />
          <AitFeature Name="msvcrt.dll!strspn" />
          <AitFeature Name="msvcrt.dll!strstr" />
          <AitFeature Name="msvcrt.dll!strtol" />
          <AitFeature Name="msvcrt.dll!strtoul" />
          <AitFeature Name="msvcrt.dll!tolower" />
          <AitFeature Name="msvcrt.dll!toupper" />
          <AitFeature Name="msvcrt.dll!ungetc" />
          <AitFeature Name="msvcrt.dll!vfprintf" />
          <AitFeature Name="msvcrt.dll!wcslen" />
        </AitCategory>
        <AitCategory Id="ApiDynamic">
          <AitFeature Name="kernel32.dll!GetSystemTimePreciseAsFileTime" />
          <AitFeature Name="kernel32.dll!SetWaitableTimer" />
          <AitFeature Name="kernel32.dll!WaitForSingleObject" />
          <AitFeature Name="opengl32.dll!glBegin" />
          <AitFeature Name="opengl32.dll!glBindTexture" />
          <AitFeature Name="opengl32.dll!glCallList" />
          <AitFeature Name="opengl32.dll!glClear" />
          <AitFeature Name="opengl32.dll!glClearColor" />
          <AitFeature Name="opengl32.dll!glDeleteLists" />
          <AitFeature Name="opengl32.dll!glDeleteTextures" />
          <AitFeature Name="opengl32.dll!glDisable" />
          <AitFeature Name="opengl32.dll!glEnable" />
          <AitFeature Name="opengl32.dll!glEnableClientState" />
          <AitFeature Name="opengl32.dll!glEnd" />
          <AitFeature Name="opengl32.dll!glEndList" />
          <AitFeature Name="opengl32.dll!glGenLists" />
          <AitFeature Name="opengl32.dll!glGenTextures" />
          <AitFeature Name="opengl32.dll!glGetIntegerv" />
          <AitFeature Name="opengl32.dll!glGetString" />
          <AitFeature Name="opengl32.dll!glIsList" />
          <AitFeature Name="opengl32.dll!glLoadIdentity" />
          <AitFeature Name="opengl32.dll!glMatrixMode" />
          <AitFeature Name="opengl32.dll!glNewList" />
          <AitFeature Name="opengl32.dll!glShadeModel" />
          <AitFeature Name="opengl32.dll!glTexCoord2f" />
          <AitFeature Name="opengl32.dll!glTexImage2D" />
          <AitFeature Name="opengl32.dll!glTexParameteri" />
          <AitFeature Name="opengl32.dll!glTexSubImage2D" />
          <AitFeature Name="opengl32.dll!glVertex2f" />
          <AitFeature Name="opengl32.dll!glViewport" />
          <AitFeature Name="msvcrt.dll!cos" />
          <AitFeature Name="msvcrt.dll!log" />
          <AitFeature Name="msvcrt.dll!pow" />
          <AitFeature Name="msvcrt.dll!sin" />
          <AitFeature Name="msvcrt.dll!system" />
        </AitCategory>
      </AitFile>
    </AitStaticAnalysis>
  </DEPENDENCY_INFORMATION>
</REPORT>